{"wsi_id": "001A", "tiles": [{"annotation_id": "7b6aff71-439e-4ec6-b615-8afb25797823", "tile_id": "tile_0_0", "x": 0, "y": 0, "xmin": 33270.0, "ymin": 51998.0, "xmax": 33543.2, "ymax": 52235.95, "lymphome_probability": 0.874433787693768}, {"annotation_id": "7b6aff71-439e-4ec6-b615-8afb25797823", "tile_id": "tile_0_1", "x": 0, "y": 1, "xmin": 33270.0, "ymin": 52235.95, "xmax": 33543.2, "ymax": 52473.9, "lymphome_probability": 0.5249319301927003}, {"annotation_id": "7b6aff71-439e-4ec6-b615-8afb25797823", "tile_id": "tile_0_2", "x": 0, "y": 2, "xmin": 33270.0, "ymin": 52473.9, "xmax": 33543.2, "ymax": 52711.85, "lymphome_probability": 0.37810861364678106}, {"annotation_id": "7b6aff71-439e-4ec6-b615-8afb25797823", "tile_id": "tile_0_3", "x": 0, "y": 3, "xmin": 33270.0, "ymin": 52711.85, "xmax": 33543.2, "ymax": 52949.8, "lymphome_probability": 0.3282187270803235}, {"annotation_id": "7b6aff71-439e-4ec6-b615-8afb25797823", "tile_id": "tile_0_4", "x": 0, "y": 4, "xmin": 33270.0, "ymin": 52949.8, "xmax": 33543.2, "ymax": 53187.75, "lymphome_probability": 0.6789193355441246}, {"annotation_id": "7b6aff71-439e-4ec6-b615-8afb25797823", "tile_id": "tile_0_5", "x": 0, "y": 5, "xmin": 33270.0, "ymin": 53187.75, "xmax": 33543.2, "ymax": 53425.7, "lymphome_probability": 0.7160993929550287}, {"annotation_id": "7b6aff71-439e-4ec6-b615-8afb25797823", "tile_id": "tile_0_6", "x": 0, "y": 6, "xmin": 33270.0, "ymin": 53425.7, "xmax": 33543.2, "ymax": 53663.65, "lymphome_probability": 0.33073571094592347}, {"annotation_id": "7b6aff71-439e-4ec6-b615-8afb25797823", "tile_id": "tile_0_7", "x": 0, "y": 7, "xmin": 33270.0, "ymin": 53663.65, "xmax": 33543.2, "ymax": 53901.6, "lymphome_probability": 0.8529086179143287}, {"annotation_id": "7b6aff71-439e-4ec6-b615-8afb25797823", "tile_id": "tile_0_8", "x": 0, "y": 8, "xmin": 33270.0, "ymin": 53901.6, "xmax": 33543.2, "ymax": 54139.55, "lymphome_probability": 0.2646216395462516}, {"annotation_id": "7b6aff71-439e-4ec6-b615-8afb25797823", "tile_id": "tile_0_9", "x": 0, "y": 9, "xmin": 33270.0, "ymin": 54139.55, "xmax": 33543.2, "ymax": 54377.5, "lymphome_probability": 0.17296012641560377}, {"annotation_id": "7b6aff71-439e-4ec6-b615-8afb25797823", "tile_id": "tile_0_10", "x": 0, "y": 10, "xmin": 33270.0, "ymin": 54377.5, "xmax": 33543.2, "ymax": 54615.45, "lymphome_probability": 0.028701721285545045}, {"annotation_id": "7b6aff71-439e-4ec6-b615-8afb25797823", "tile_id": "tile_0_11", "x": 0, "y": 11, "xmin": 33270.0, "ymin": 54615.45, "xmax": 33543.2, "ymax": 54853.4, "lymphome_probability": 0.002311821094671651}, {"annotation_id": "7b6aff71-439e-4ec6-b615-8afb25797823", "tile_id": "tile_0_12", "x": 0, "y": 12, "xmin": 33270.0, "ymin": 54853.4, "xmax": 33543.2, "ymax": 55091.35, "lymphome_probability": 0.8132679894971628}, {"annotation_id": "7b6aff71-439e-4ec6-b615-8afb25797823", "tile_id": "tile_0_13", "x": 0, "y": 13, "xmin": 33270.0, "ymin": 55091.35, "xmax": 33543.2, "ymax": 55329.3, "lymphome_probability": 0.08643380296040548}, {"annotation_id": "7b6aff71-439e-4ec6-b615-8afb25797823", "tile_id": "tile_0_14", "x": 0, "y": 14, "xmin": 33270.0, "ymin": 55329.3, "xmax": 33543.2, "ymax": 55567.25, "lymphome_probability": 0.4662899837883404}, {"annotation_id": "7b6aff71-439e-4ec6-b615-8afb25797823", "tile_id": "tile_0_15", "x": 0, "y": 15, "xmin": 33270.0, "ymin": 55567.25, "xmax": 33543.2, "ymax": 55805.2, "lymphome_probability": 0.18628781272706152}, {"annotation_id": "7b6aff71-439e-4ec6-b615-8afb25797823", "tile_id": "tile_0_16", "x": 0, "y": 16, "xmin": 33270.0, "ymin": 55805.2, "xmax": 33543.2, "ymax": 56043.15, "lymphome_probability": 0.21853725784527434}, {"annotation_id": "7b6aff71-439e-4ec6-b615-8afb25797823", "tile_id": "tile_0_17", "x": 0, "y": 17, "xmin": 33270.0, "ymin": 56043.15, "xmax": 33543.2, "ymax": 56281.1, "lymphome_probability": 0.21867791355628274}, {"annotation_id": "7b6aff71-439e-4ec6-b615-8afb25797823", "tile_id": "tile_0_18", "x": 0, "y": 18, "xmin": 33270.0, "ymin": 56281.1, "xmax": 33543.2, "ymax": 56519.05, "lymphome_probability": 0.6734343676300646}, {"annotation_id": "7b6aff71-439e-4ec6-b615-8afb25797823", "tile_id": "tile_0_19", "x": 0, "y": 19, "xmin": 33270.0, "ymin": 56519.05, "xmax": 33543.2, "ymax": 56757.0, "lymphome_probability": 0.9816598446376369}, {"annotation_id": "7b6aff71-439e-4ec6-b615-8afb25797823", "tile_id": "tile_1_0", "x": 1, "y": 0, "xmin": 33543.2, "ymin": 51998.0, "xmax": 33816.4, "ymax": 52235.95, "lymphome_probability": 0.17267211123748594}, {"annotation_id": "7b6aff71-439e-4ec6-b615-8afb25797823", "tile_id": "tile_1_1", "x": 1, "y": 1, "xmin": 33543.2, "ymin": 52235.95, "xmax": 33816.4, "ymax": 52473.9, "lymphome_probability": 0.13795130509939568}, {"annotation_id": "7b6aff71-439e-4ec6-b615-8afb25797823", "tile_id": "tile_1_2", "x": 1, "y": 2, "xmin": 33543.2, "ymin": 52473.9, "xmax": 33816.4, "ymax": 52711.85, "lymphome_probability": 0.6961479793136784}, {"annotation_id": "7b6aff71-439e-4ec6-b615-8afb25797823", "tile_id": "tile_1_3", "x": 1, "y": 3, "xmin": 33543.2, "ymin": 52711.85, "xmax": 33816.4, "ymax": 52949.8, "lymphome_probability": 0.0055148410508004675}, {"annotation_id": "7b6aff71-439e-4ec6-b615-8afb25797823", "tile_id": "tile_1_4", "x": 1, "y": 4, "xmin": 33543.2, "ymin": 52949.8, "xmax": 33816.4, "ymax": 53187.75, "lymphome_probability": 0.798696432105519}, {"annotation_id": "7b6aff71-439e-4ec6-b615-8afb25797823", "tile_id": "tile_1_5", "x": 1, "y": 5, "xmin": 33543.2, "ymin": 53187.75, "xmax": 33816.4, "ymax": 53425.7, "lymphome_probability": 0.14408513471130913}, {"annotation_id": "7b6aff71-439e-4ec6-b615-8afb25797823", "tile_id": "tile_1_6", "x": 1, "y": 6, "xmin": 33543.2, "ymin": 53425.7, "xmax": 33816.4, "ymax": 53663.65, "lymphome_probability": 0.8146647059944243}, {"annotation_id": "7b6aff71-439e-4ec6-b615-8afb25797823", "tile_id": "tile_1_7", "x": 1, "y": 7, "xmin": 33543.2, "ymin": 53663.65, "xmax": 33816.4, "ymax": 53901.6, "lymphome_probability": 0.029581105316874856}, {"annotation_id": "7b6aff71-439e-4ec6-b615-8afb25797823", "tile_id": "tile_1_8", "x": 1, "y": 8, "xmin": 33543.2, "ymin": 53901.6, "xmax": 33816.4, "ymax": 54139.55, "lymphome_probability": 0.45383782414326757}, {"annotation_id": "7b6aff71-439e-4ec6-b615-8afb25797823", "tile_id": "tile_1_9", "x": 1, "y": 9, "xmin": 33543.2, "ymin": 54139.55, "xmax": 33816.4, "ymax": 54377.5, "lymphome_probability": 0.9557714283488965}, {"annotation_id": "7b6aff71-439e-4ec6-b615-8afb25797823", "tile_id": "tile_1_10", "x": 1, "y": 10, "xmin": 33543.2, "ymin": 54377.5, "xmax": 33816.4, "ymax": 54615.45, "lymphome_probability": 0.9059599600765224}, {"annotation_id": "7b6aff71-439e-4ec6-b615-8afb25797823", "tile_id": "tile_1_11", "x": 1, "y": 11, "xmin": 33543.2, "ymin": 54615.45, "xmax": 33816.4, "ymax": 54853.4, "lymphome_probability": 0.20862178141707055}, {"annotation_id": "7b6aff71-439e-4ec6-b615-8afb25797823", "tile_id": "tile_1_12", "x": 1, "y": 12, "xmin": 33543.2, "ymin": 54853.4, "xmax": 33816.4, "ymax": 55091.35, "lymphome_probability": 0.2882272922416236}, {"annotation_id": "7b6aff71-439e-4ec6-b615-8afb25797823", "tile_id": "tile_1_13", "x": 1, "y": 13, "xmin": 33543.2, "ymin": 55091.35, "xmax": 33816.4, "ymax": 55329.3, "lymphome_probability": 0.42980292804406117}, {"annotation_id": "7b6aff71-439e-4ec6-b615-8afb25797823", "tile_id": "tile_1_14", "x": 1, "y": 14, "xmin": 33543.2, "ymin": 55329.3, "xmax": 33816.4, "ymax": 55567.25, "lymphome_probability": 0.5328426205558118}, {"annotation_id": "7b6aff71-439e-4ec6-b615-8afb25797823", "tile_id": "tile_1_15", "x": 1, "y": 15, "xmin": 33543.2, "ymin": 55567.25, "xmax": 33816.4, "ymax": 55805.2, "lymphome_probability": 0.7541974679090889}, {"annotation_id": "7b6aff71-439e-4ec6-b615-8afb25797823", "tile_id": "tile_1_16", "x": 1, "y": 16, "xmin": 33543.2, "ymin": 55805.2, "xmax": 33816.4, "ymax": 56043.15, "lymphome_probability": 0.6198727250871502}, {"annotation_id": "7b6aff71-439e-4ec6-b615-8afb25797823", "tile_id": "tile_1_17", "x": 1, "y": 17, "xmin": 33543.2, "ymin": 56043.15, "xmax": 33816.4, "ymax": 56281.1, "lymphome_probability": 0.23584647066942}, {"annotation_id": "7b6aff71-439e-4ec6-b615-8afb25797823", "tile_id": "tile_1_18", "x": 1, "y": 18, "xmin": 33543.2, "ymin": 56281.1, "xmax": 33816.4, "ymax": 56519.05, "lymphome_probability": 0.8395021008553266}, {"annotation_id": "7b6aff71-439e-4ec6-b615-8afb25797823", "tile_id": "tile_1_19", "x": 1, "y": 19, "xmin": 33543.2, "ymin": 56519.05, "xmax": 33816.4, "ymax": 56757.0, "lymphome_probability": 0.49219499910780096}, {"annotation_id": "7b6aff71-439e-4ec6-b615-8afb25797823", "tile_id": "tile_2_0", "x": 2, "y": 0, "xmin": 33816.4, "ymin": 51998.0, "xmax": 34089.6, "ymax": 52235.95, "lymphome_probability": 0.5194232732291021}, {"annotation_id": "7b6aff71-439e-4ec6-b615-8afb25797823", "tile_id": "tile_2_1", "x": 2, "y": 1, "xmin": 33816.4, "ymin": 52235.95, "xmax": 34089.6, "ymax": 52473.9, "lymphome_probability": 0.22756670877103202}, {"annotation_id": "7b6aff71-439e-4ec6-b615-8afb25797823", "tile_id": "tile_2_2", "x": 2, "y": 2, "xmin": 33816.4, "ymin": 52473.9, "xmax": 34089.6, "ymax": 52711.85, "lymphome_probability": 0.3120937000369557}, {"annotation_id": "7b6aff71-439e-4ec6-b615-8afb25797823", "tile_id": "tile_2_3", "x": 2, "y": 3, "xmin": 33816.4, "ymin": 52711.85, "xmax": 34089.6, "ymax": 52949.8, "lymphome_probability": 0.7832766861228365}, {"annotation_id": "7b6aff71-439e-4ec6-b615-8afb25797823", "tile_id": "tile_2_4", "x": 2, "y": 4, "xmin": 33816.4, "ymin": 52949.8, "xmax": 34089.6, "ymax": 53187.75, "lymphome_probability": 0.6963235011326752}, {"annotation_id": "7b6aff71-439e-4ec6-b615-8afb25797823", "tile_id": "tile_2_5", "x": 2, "y": 5, "xmin": 33816.4, "ymin": 53187.75, "xmax": 34089.6, "ymax": 53425.7, "lymphome_probability": 0.33987724394351826}, {"annotation_id": "7b6aff71-439e-4ec6-b615-8afb25797823", "tile_id": "tile_2_6", "x": 2, "y": 6, "xmin": 33816.4, "ymin": 53425.7, "xmax": 34089.6, "ymax": 53663.65, "lymphome_probability": 0.037185102219666644}, {"annotation_id": "7b6aff71-439e-4ec6-b615-8afb25797823", "tile_id": "tile_2_7", "x": 2, "y": 7, "xmin": 33816.4, "ymin": 53663.65, "xmax": 34089.6, "ymax": 53901.6, "lymphome_probability": 0.8539307345729864}, {"annotation_id": "7b6aff71-439e-4ec6-b615-8afb25797823", "tile_id": "tile_2_8", "x": 2, "y": 8, "xmin": 33816.4, "ymin": 53901.6, "xmax": 34089.6, "ymax": 54139.55, "lymphome_probability": 0.8360310856778566}, {"annotation_id": "7b6aff71-439e-4ec6-b615-8afb25797823", "tile_id": "tile_2_9", "x": 2, "y": 9, "xmin": 33816.4, "ymin": 54139.55, "xmax": 34089.6, "ymax": 54377.5, "lymphome_probability": 0.9387480110703585}, {"annotation_id": "7b6aff71-439e-4ec6-b615-8afb25797823", "tile_id": "tile_2_10", "x": 2, "y": 10, "xmin": 33816.4, "ymin": 54377.5, "xmax": 34089.6, "ymax": 54615.45, "lymphome_probability": 0.11796676252869731}, {"annotation_id": "7b6aff71-439e-4ec6-b615-8afb25797823", "tile_id": "tile_2_11", "x": 2, "y": 11, "xmin": 33816.4, "ymin": 54615.45, "xmax": 34089.6, "ymax": 54853.4, "lymphome_probability": 0.33952853972237085}, {"annotation_id": "7b6aff71-439e-4ec6-b615-8afb25797823", "tile_id": "tile_2_12", "x": 2, "y": 12, "xmin": 33816.4, "ymin": 54853.4, "xmax": 34089.6, "ymax": 55091.35, "lymphome_probability": 0.048902700369169994}, {"annotation_id": "7b6aff71-439e-4ec6-b615-8afb25797823", "tile_id": "tile_2_13", "x": 2, "y": 13, "xmin": 33816.4, "ymin": 55091.35, "xmax": 34089.6, "ymax": 55329.3, "lymphome_probability": 0.4834945129061975}, {"annotation_id": "7b6aff71-439e-4ec6-b615-8afb25797823", "tile_id": "tile_2_14", "x": 2, "y": 14, "xmin": 33816.4, "ymin": 55329.3, "xmax": 34089.6, "ymax": 55567.25, "lymphome_probability": 0.4228057380930291}, {"annotation_id": "7b6aff71-439e-4ec6-b615-8afb25797823", "tile_id": "tile_2_15", "x": 2, "y": 15, "xmin": 33816.4, "ymin": 55567.25, "xmax": 34089.6, "ymax": 55805.2, "lymphome_probability": 0.43923767875868147}, {"annotation_id": "7b6aff71-439e-4ec6-b615-8afb25797823", "tile_id": "tile_2_16", "x": 2, "y": 16, "xmin": 33816.4, "ymin": 55805.2, "xmax": 34089.6, "ymax": 56043.15, "lymphome_probability": 0.6450196528126975}, {"annotation_id": "7b6aff71-439e-4ec6-b615-8afb25797823", "tile_id": "tile_2_17", "x": 2, "y": 17, "xmin": 33816.4, "ymin": 56043.15, "xmax": 34089.6, "ymax": 56281.1, "lymphome_probability": 0.28937496236704396}, {"annotation_id": "7b6aff71-439e-4ec6-b615-8afb25797823", "tile_id": "tile_2_18", "x": 2, "y": 18, "xmin": 33816.4, "ymin": 56281.1, "xmax": 34089.6, "ymax": 56519.05, "lymphome_probability": 0.914567700411333}, {"annotation_id": "7b6aff71-439e-4ec6-b615-8afb25797823", "tile_id": "tile_2_19", "x": 2, "y": 19, "xmin": 33816.4, "ymin": 56519.05, "xmax": 34089.6, "ymax": 56757.0, "lymphome_probability": 0.27019807599387924}, {"annotation_id": "7b6aff71-439e-4ec6-b615-8afb25797823", "tile_id": "tile_3_0", "x": 3, "y": 0, "xmin": 34089.6, "ymin": 51998.0, "xmax": 34362.8, "ymax": 52235.95, "lymphome_probability": 0.16269467141402938}, {"annotation_id": "7b6aff71-439e-4ec6-b615-8afb25797823", "tile_id": "tile_3_1", "x": 3, "y": 1, "xmin": 34089.6, "ymin": 52235.95, "xmax": 34362.8, "ymax": 52473.9, "lymphome_probability": 0.8646723946731968}, {"annotation_id": "7b6aff71-439e-4ec6-b615-8afb25797823", "tile_id": "tile_3_2", "x": 3, "y": 2, "xmin": 34089.6, "ymin": 52473.9, "xmax": 34362.8, "ymax": 52711.85, "lymphome_probability": 0.2607740986657746}, {"annotation_id": "7b6aff71-439e-4ec6-b615-8afb25797823", "tile_id": "tile_3_3", "x": 3, "y": 3, "xmin": 34089.6, "ymin": 52711.85, "xmax": 34362.8, "ymax": 52949.8, "lymphome_probability": 0.6104774339237032}, {"annotation_id": "7b6aff71-439e-4ec6-b615-8afb25797823", "tile_id": "tile_3_4", "x": 3, "y": 4, "xmin": 34089.6, "ymin": 52949.8, "xmax": 34362.8, "ymax": 53187.75, "lymphome_probability": 0.7435439830044295}, {"annotation_id": "7b6aff71-439e-4ec6-b615-8afb25797823", "tile_id": "tile_3_5", "x": 3, "y": 5, "xmin": 34089.6, "ymin": 53187.75, "xmax": 34362.8, "ymax": 53425.7, "lymphome_probability": 0.7624476226853955}, {"annotation_id": "7b6aff71-439e-4ec6-b615-8afb25797823", "tile_id": "tile_3_6", "x": 3, "y": 6, "xmin": 34089.6, "ymin": 53425.7, "xmax": 34362.8, "ymax": 53663.65, "lymphome_probability": 0.4041530489491706}, {"annotation_id": "7b6aff71-439e-4ec6-b615-8afb25797823", "tile_id": "tile_3_7", "x": 3, "y": 7, "xmin": 34089.6, "ymin": 53663.65, "xmax": 34362.8, "ymax": 53901.6, "lymphome_probability": 0.35904749677944847}, {"annotation_id": "7b6aff71-439e-4ec6-b615-8afb25797823", "tile_id": "tile_3_8", "x": 3, "y": 8, "xmin": 34089.6, "ymin": 53901.6, "xmax": 34362.8, "ymax": 54139.55, "lymphome_probability": 0.8737525417540306}, {"annotation_id": "7b6aff71-439e-4ec6-b615-8afb25797823", "tile_id": "tile_3_9", "x": 3, "y": 9, "xmin": 34089.6, "ymin": 54139.55, "xmax": 34362.8, "ymax": 54377.5, "lymphome_probability": 0.06437335536981048}, {"annotation_id": "7b6aff71-439e-4ec6-b615-8afb25797823", "tile_id": "tile_3_10", "x": 3, "y": 10, "xmin": 34089.6, "ymin": 54377.5, "xmax": 34362.8, "ymax": 54615.45, "lymphome_probability": 0.9577734749737669}, {"annotation_id": "7b6aff71-439e-4ec6-b615-8afb25797823", "tile_id": "tile_3_11", "x": 3, "y": 11, "xmin": 34089.6, "ymin": 54615.45, "xmax": 34362.8, "ymax": 54853.4, "lymphome_probability": 0.19720796440341704}, {"annotation_id": "7b6aff71-439e-4ec6-b615-8afb25797823", "tile_id": "tile_3_12", "x": 3, "y": 12, "xmin": 34089.6, "ymin": 54853.4, "xmax": 34362.8, "ymax": 55091.35, "lymphome_probability": 0.8935926862532623}, {"annotation_id": "7b6aff71-439e-4ec6-b615-8afb25797823", "tile_id": "tile_3_13", "x": 3, "y": 13, "xmin": 34089.6, "ymin": 55091.35, "xmax": 34362.8, "ymax": 55329.3, "lymphome_probability": 0.9545311788374659}, {"annotation_id": "7b6aff71-439e-4ec6-b615-8afb25797823", "tile_id": "tile_3_14", "x": 3, "y": 14, "xmin": 34089.6, "ymin": 55329.3, "xmax": 34362.8, "ymax": 55567.25, "lymphome_probability": 0.31178494151835334}, {"annotation_id": "7b6aff71-439e-4ec6-b615-8afb25797823", "tile_id": "tile_3_15", "x": 3, "y": 15, "xmin": 34089.6, "ymin": 55567.25, "xmax": 34362.8, "ymax": 55805.2, "lymphome_probability": 0.9062859160064476}, {"annotation_id": "7b6aff71-439e-4ec6-b615-8afb25797823", "tile_id": "tile_3_16", "x": 3, "y": 16, "xmin": 34089.6, "ymin": 55805.2, "xmax": 34362.8, "ymax": 56043.15, "lymphome_probability": 0.992011816742796}, {"annotation_id": "7b6aff71-439e-4ec6-b615-8afb25797823", "tile_id": "tile_3_17", "x": 3, "y": 17, "xmin": 34089.6, "ymin": 56043.15, "xmax": 34362.8, "ymax": 56281.1, "lymphome_probability": 0.9408957018881405}, {"annotation_id": "7b6aff71-439e-4ec6-b615-8afb25797823", "tile_id": "tile_3_18", "x": 3, "y": 18, "xmin": 34089.6, "ymin": 56281.1, "xmax": 34362.8, "ymax": 56519.05, "lymphome_probability": 0.10643723901107616}, {"annotation_id": "7b6aff71-439e-4ec6-b615-8afb25797823", "tile_id": "tile_3_19", "x": 3, "y": 19, "xmin": 34089.6, "ymin": 56519.05, "xmax": 34362.8, "ymax": 56757.0, "lymphome_probability": 0.48278942738040265}, {"annotation_id": "7b6aff71-439e-4ec6-b615-8afb25797823", "tile_id": "tile_4_0", "x": 4, "y": 0, "xmin": 34362.8, "ymin": 51998.0, "xmax": 34636.0, "ymax": 52235.95, "lymphome_probability": 0.4724413847723452}, {"annotation_id": "7b6aff71-439e-4ec6-b615-8afb25797823", "tile_id": "tile_4_1", "x": 4, "y": 1, "xmin": 34362.8, "ymin": 52235.95, "xmax": 34636.0, "ymax": 52473.9, "lymphome_probability": 0.09252212234098223}, {"annotation_id": "7b6aff71-439e-4ec6-b615-8afb25797823", "tile_id": "tile_4_2", "x": 4, "y": 2, "xmin": 34362.8, "ymin": 52473.9, "xmax": 34636.0, "ymax": 52711.85, "lymphome_probability": 0.6361818995312639}, {"annotation_id": "7b6aff71-439e-4ec6-b615-8afb25797823", "tile_id": "tile_4_3", "x": 4, "y": 3, "xmin": 34362.8, "ymin": 52711.85, "xmax": 34636.0, "ymax": 52949.8, "lymphome_probability": 0.7655222005655826}, {"annotation_id": "7b6aff71-439e-4ec6-b615-8afb25797823", "tile_id": "tile_4_4", "x": 4, "y": 4, "xmin": 34362.8, "ymin": 52949.8, "xmax": 34636.0, "ymax": 53187.75, "lymphome_probability": 0.8387391034359654}, {"annotation_id": "7b6aff71-439e-4ec6-b615-8afb25797823", "tile_id": "tile_4_5", "x": 4, "y": 5, "xmin": 34362.8, "ymin": 53187.75, "xmax": 34636.0, "ymax": 53425.7, "lymphome_probability": 0.32946019967590423}, {"annotation_id": "7b6aff71-439e-4ec6-b615-8afb25797823", "tile_id": "tile_4_6", "x": 4, "y": 6, "xmin": 34362.8, "ymin": 53425.7, "xmax": 34636.0, "ymax": 53663.65, "lymphome_probability": 0.5533277822268985}, {"annotation_id": "7b6aff71-439e-4ec6-b615-8afb25797823", "tile_id": "tile_4_7", "x": 4, "y": 7, "xmin": 34362.8, "ymin": 53663.65, "xmax": 34636.0, "ymax": 53901.6, "lymphome_probability": 0.00814369485262989}, {"annotation_id": "7b6aff71-439e-4ec6-b615-8afb25797823", "tile_id": "tile_4_8", "x": 4, "y": 8, "xmin": 34362.8, "ymin": 53901.6, "xmax": 34636.0, "ymax": 54139.55, "lymphome_probability": 0.8252699869534014}, {"annotation_id": "7b6aff71-439e-4ec6-b615-8afb25797823", "tile_id": "tile_4_9", "x": 4, "y": 9, "xmin": 34362.8, "ymin": 54139.55, "xmax": 34636.0, "ymax": 54377.5, "lymphome_probability": 0.5433628052989256}, {"annotation_id": "7b6aff71-439e-4ec6-b615-8afb25797823", "tile_id": "tile_4_10", "x": 4, "y": 10, "xmin": 34362.8, "ymin": 54377.5, "xmax": 34636.0, "ymax": 54615.45, "lymphome_probability": 0.8601634225940993}, {"annotation_id": "7b6aff71-439e-4ec6-b615-8afb25797823", "tile_id": "tile_4_11", "x": 4, "y": 11, "xmin": 34362.8, "ymin": 54615.45, "xmax": 34636.0, "ymax": 54853.4, "lymphome_probability": 0.5233257123387803}, {"annotation_id": "7b6aff71-439e-4ec6-b615-8afb25797823", "tile_id": "tile_4_12", "x": 4, "y": 12, "xmin": 34362.8, "ymin": 54853.4, "xmax": 34636.0, "ymax": 55091.35, "lymphome_probability": 0.036519610698463656}, {"annotation_id": "7b6aff71-439e-4ec6-b615-8afb25797823", "tile_id": "tile_4_13", "x": 4, "y": 13, "xmin": 34362.8, "ymin": 55091.35, "xmax": 34636.0, "ymax": 55329.3, "lymphome_probability": 0.9934061551360798}, {"annotation_id": "7b6aff71-439e-4ec6-b615-8afb25797823", "tile_id": "tile_4_14", "x": 4, "y": 14, "xmin": 34362.8, "ymin": 55329.3, "xmax": 34636.0, "ymax": 55567.25, "lymphome_probability": 0.8685669272609807}, {"annotation_id": "7b6aff71-439e-4ec6-b615-8afb25797823", "tile_id": "tile_4_15", "x": 4, "y": 15, "xmin": 34362.8, "ymin": 55567.25, "xmax": 34636.0, "ymax": 55805.2, "lymphome_probability": 0.5779029128786478}, {"annotation_id": "7b6aff71-439e-4ec6-b615-8afb25797823", "tile_id": "tile_4_16", "x": 4, "y": 16, "xmin": 34362.8, "ymin": 55805.2, "xmax": 34636.0, "ymax": 56043.15, "lymphome_probability": 0.10828550691287886}, {"annotation_id": "7b6aff71-439e-4ec6-b615-8afb25797823", "tile_id": "tile_4_17", "x": 4, "y": 17, "xmin": 34362.8, "ymin": 56043.15, "xmax": 34636.0, "ymax": 56281.1, "lymphome_probability": 0.7501849864527608}, {"annotation_id": "7b6aff71-439e-4ec6-b615-8afb25797823", "tile_id": "tile_4_18", "x": 4, "y": 18, "xmin": 34362.8, "ymin": 56281.1, "xmax": 34636.0, "ymax": 56519.05, "lymphome_probability": 0.42367363025428917}, {"annotation_id": "7b6aff71-439e-4ec6-b615-8afb25797823", "tile_id": "tile_4_19", "x": 4, "y": 19, "xmin": 34362.8, "ymin": 56519.05, "xmax": 34636.0, "ymax": 56757.0, "lymphome_probability": 0.8228126693555119}, {"annotation_id": "7b6aff71-439e-4ec6-b615-8afb25797823", "tile_id": "tile_5_0", "x": 5, "y": 0, "xmin": 34636.0, "ymin": 51998.0, "xmax": 34909.2, "ymax": 52235.95, "lymphome_probability": 0.3151249741530261}, {"annotation_id": "7b6aff71-439e-4ec6-b615-8afb25797823", "tile_id": "tile_5_1", "x": 5, "y": 1, "xmin": 34636.0, "ymin": 52235.95, "xmax": 34909.2, "ymax": 52473.9, "lymphome_probability": 0.9644533087101851}, {"annotation_id": "7b6aff71-439e-4ec6-b615-8afb25797823", "tile_id": "tile_5_2", "x": 5, "y": 2, "xmin": 34636.0, "ymin": 52473.9, "xmax": 34909.2, "ymax": 52711.85, "lymphome_probability": 0.3199727598758725}, {"annotation_id": "7b6aff71-439e-4ec6-b615-8afb25797823", "tile_id": "tile_5_3", "x": 5, "y": 3, "xmin": 34636.0, "ymin": 52711.85, "xmax": 34909.2, "ymax": 52949.8, "lymphome_probability": 0.9999498419018642}, {"annotation_id": "7b6aff71-439e-4ec6-b615-8afb25797823", "tile_id": "tile_5_4", "x": 5, "y": 4, "xmin": 34636.0, "ymin": 52949.8, "xmax": 34909.2, "ymax": 53187.75, "lymphome_probability": 0.6482115213200978}, {"annotation_id": "7b6aff71-439e-4ec6-b615-8afb25797823", "tile_id": "tile_5_5", "x": 5, "y": 5, "xmin": 34636.0, "ymin": 53187.75, "xmax": 34909.2, "ymax": 53425.7, "lymphome_probability": 0.28005802895987064}, {"annotation_id": "7b6aff71-439e-4ec6-b615-8afb25797823", "tile_id": "tile_5_6", "x": 5, "y": 6, "xmin": 34636.0, "ymin": 53425.7, "xmax": 34909.2, "ymax": 53663.65, "lymphome_probability": 0.412599217692469}, {"annotation_id": "7b6aff71-439e-4ec6-b615-8afb25797823", "tile_id": "tile_5_7", "x": 5, "y": 7, "xmin": 34636.0, "ymin": 53663.65, "xmax": 34909.2, "ymax": 53901.6, "lymphome_probability": 0.6114674364982884}, {"annotation_id": "7b6aff71-439e-4ec6-b615-8afb25797823", "tile_id": "tile_5_8", "x": 5, "y": 8, "xmin": 34636.0, "ymin": 53901.6, "xmax": 34909.2, "ymax": 54139.55, "lymphome_probability": 0.4750579517657909}, {"annotation_id": "7b6aff71-439e-4ec6-b615-8afb25797823", "tile_id": "tile_5_9", "x": 5, "y": 9, "xmin": 34636.0, "ymin": 54139.55, "xmax": 34909.2, "ymax": 54377.5, "lymphome_probability": 0.7379259870811594}, {"annotation_id": "7b6aff71-439e-4ec6-b615-8afb25797823", "tile_id": "tile_5_10", "x": 5, "y": 10, "xmin": 34636.0, "ymin": 54377.5, "xmax": 34909.2, "ymax": 54615.45, "lymphome_probability": 0.3904201779489358}, {"annotation_id": "7b6aff71-439e-4ec6-b615-8afb25797823", "tile_id": "tile_5_11", "x": 5, "y": 11, "xmin": 34636.0, "ymin": 54615.45, "xmax": 34909.2, "ymax": 54853.4, "lymphome_probability": 0.4305741840827013}, {"annotation_id": "7b6aff71-439e-4ec6-b615-8afb25797823", "tile_id": "tile_5_12", "x": 5, "y": 12, "xmin": 34636.0, "ymin": 54853.4, "xmax": 34909.2, "ymax": 55091.35, "lymphome_probability": 0.14329568481372001}, {"annotation_id": "7b6aff71-439e-4ec6-b615-8afb25797823", "tile_id": "tile_5_13", "x": 5, "y": 13, "xmin": 34636.0, "ymin": 55091.35, "xmax": 34909.2, "ymax": 55329.3, "lymphome_probability": 0.9295473634759193}, {"annotation_id": "7b6aff71-439e-4ec6-b615-8afb25797823", "tile_id": "tile_5_14", "x": 5, "y": 14, "xmin": 34636.0, "ymin": 55329.3, "xmax": 34909.2, "ymax": 55567.25, "lymphome_probability": 0.8437345136664919}, {"annotation_id": "7b6aff71-439e-4ec6-b615-8afb25797823", "tile_id": "tile_5_15", "x": 5, "y": 15, "xmin": 34636.0, "ymin": 55567.25, "xmax": 34909.2, "ymax": 55805.2, "lymphome_probability": 0.0033959852348409703}, {"annotation_id": "7b6aff71-439e-4ec6-b615-8afb25797823", "tile_id": "tile_5_16", "x": 5, "y": 16, "xmin": 34636.0, "ymin": 55805.2, "xmax": 34909.2, "ymax": 56043.15, "lymphome_probability": 0.19730083063208914}, {"annotation_id": "7b6aff71-439e-4ec6-b615-8afb25797823", "tile_id": "tile_5_17", "x": 5, "y": 17, "xmin": 34636.0, "ymin": 56043.15, "xmax": 34909.2, "ymax": 56281.1, "lymphome_probability": 0.8172086863724772}, {"annotation_id": "7b6aff71-439e-4ec6-b615-8afb25797823", "tile_id": "tile_5_18", "x": 5, "y": 18, "xmin": 34636.0, "ymin": 56281.1, "xmax": 34909.2, "ymax": 56519.05, "lymphome_probability": 0.9473064522287374}, {"annotation_id": "7b6aff71-439e-4ec6-b615-8afb25797823", "tile_id": "tile_5_19", "x": 5, "y": 19, "xmin": 34636.0, "ymin": 56519.05, "xmax": 34909.2, "ymax": 56757.0, "lymphome_probability": 0.12268667248148313}, {"annotation_id": "7b6aff71-439e-4ec6-b615-8afb25797823", "tile_id": "tile_6_0", "x": 6, "y": 0, "xmin": 34909.2, "ymin": 51998.0, "xmax": 35182.4, "ymax": 52235.95, "lymphome_probability": 0.04718257600744613}, {"annotation_id": "7b6aff71-439e-4ec6-b615-8afb25797823", "tile_id": "tile_6_1", "x": 6, "y": 1, "xmin": 34909.2, "ymin": 52235.95, "xmax": 35182.4, "ymax": 52473.9, "lymphome_probability": 0.7749489000749821}, {"annotation_id": "7b6aff71-439e-4ec6-b615-8afb25797823", "tile_id": "tile_6_2", "x": 6, "y": 2, "xmin": 34909.2, "ymin": 52473.9, "xmax": 35182.4, "ymax": 52711.85, "lymphome_probability": 0.9163520540157242}, {"annotation_id": "7b6aff71-439e-4ec6-b615-8afb25797823", "tile_id": "tile_6_3", "x": 6, "y": 3, "xmin": 34909.2, "ymin": 52711.85, "xmax": 35182.4, "ymax": 52949.8, "lymphome_probability": 0.8179214949676512}, {"annotation_id": "7b6aff71-439e-4ec6-b615-8afb25797823", "tile_id": "tile_6_4", "x": 6, "y": 4, "xmin": 34909.2, "ymin": 52949.8, "xmax": 35182.4, "ymax": 53187.75, "lymphome_probability": 0.6596323060718069}, {"annotation_id": "7b6aff71-439e-4ec6-b615-8afb25797823", "tile_id": "tile_6_5", "x": 6, "y": 5, "xmin": 34909.2, "ymin": 53187.75, "xmax": 35182.4, "ymax": 53425.7, "lymphome_probability": 0.601182615040759}, {"annotation_id": "7b6aff71-439e-4ec6-b615-8afb25797823", "tile_id": "tile_6_6", "x": 6, "y": 6, "xmin": 34909.2, "ymin": 53425.7, "xmax": 35182.4, "ymax": 53663.65, "lymphome_probability": 0.31564246647011773}, {"annotation_id": "7b6aff71-439e-4ec6-b615-8afb25797823", "tile_id": "tile_6_7", "x": 6, "y": 7, "xmin": 34909.2, "ymin": 53663.65, "xmax": 35182.4, "ymax": 53901.6, "lymphome_probability": 0.822769283256837}, {"annotation_id": "7b6aff71-439e-4ec6-b615-8afb25797823", "tile_id": "tile_6_8", "x": 6, "y": 8, "xmin": 34909.2, "ymin": 53901.6, "xmax": 35182.4, "ymax": 54139.55, "lymphome_probability": 0.3372533925380644}, {"annotation_id": "7b6aff71-439e-4ec6-b615-8afb25797823", "tile_id": "tile_6_9", "x": 6, "y": 9, "xmin": 34909.2, "ymin": 54139.55, "xmax": 35182.4, "ymax": 54377.5, "lymphome_probability": 0.6443340233489573}, {"annotation_id": "7b6aff71-439e-4ec6-b615-8afb25797823", "tile_id": "tile_6_10", "x": 6, "y": 10, "xmin": 34909.2, "ymin": 54377.5, "xmax": 35182.4, "ymax": 54615.45, "lymphome_probability": 0.27532967836726974}, {"annotation_id": "7b6aff71-439e-4ec6-b615-8afb25797823", "tile_id": "tile_6_11", "x": 6, "y": 11, "xmin": 34909.2, "ymin": 54615.45, "xmax": 35182.4, "ymax": 54853.4, "lymphome_probability": 0.32009650354494623}, {"annotation_id": "7b6aff71-439e-4ec6-b615-8afb25797823", "tile_id": "tile_6_12", "x": 6, "y": 12, "xmin": 34909.2, "ymin": 54853.4, "xmax": 35182.4, "ymax": 55091.35, "lymphome_probability": 0.33274749380381785}, {"annotation_id": "7b6aff71-439e-4ec6-b615-8afb25797823", "tile_id": "tile_6_13", "x": 6, "y": 13, "xmin": 34909.2, "ymin": 55091.35, "xmax": 35182.4, "ymax": 55329.3, "lymphome_probability": 0.43187957026161383}, {"annotation_id": "7b6aff71-439e-4ec6-b615-8afb25797823", "tile_id": "tile_6_14", "x": 6, "y": 14, "xmin": 34909.2, "ymin": 55329.3, "xmax": 35182.4, "ymax": 55567.25, "lymphome_probability": 0.3817686310048557}, {"annotation_id": "7b6aff71-439e-4ec6-b615-8afb25797823", "tile_id": "tile_6_15", "x": 6, "y": 15, "xmin": 34909.2, "ymin": 55567.25, "xmax": 35182.4, "ymax": 55805.2, "lymphome_probability": 0.15874230014967883}, {"annotation_id": "7b6aff71-439e-4ec6-b615-8afb25797823", "tile_id": "tile_6_16", "x": 6, "y": 16, "xmin": 34909.2, "ymin": 55805.2, "xmax": 35182.4, "ymax": 56043.15, "lymphome_probability": 0.37169787296732004}, {"annotation_id": "7b6aff71-439e-4ec6-b615-8afb25797823", "tile_id": "tile_6_17", "x": 6, "y": 17, "xmin": 34909.2, "ymin": 56043.15, "xmax": 35182.4, "ymax": 56281.1, "lymphome_probability": 0.041413277929415515}, {"annotation_id": "7b6aff71-439e-4ec6-b615-8afb25797823", "tile_id": "tile_6_18", "x": 6, "y": 18, "xmin": 34909.2, "ymin": 56281.1, "xmax": 35182.4, "ymax": 56519.05, "lymphome_probability": 0.7954296232425826}, {"annotation_id": "7b6aff71-439e-4ec6-b615-8afb25797823", "tile_id": "tile_6_19", "x": 6, "y": 19, "xmin": 34909.2, "ymin": 56519.05, "xmax": 35182.4, "ymax": 56757.0, "lymphome_probability": 0.5515431468639376}, {"annotation_id": "7b6aff71-439e-4ec6-b615-8afb25797823", "tile_id": "tile_7_0", "x": 7, "y": 0, "xmin": 35182.4, "ymin": 51998.0, "xmax": 35455.6, "ymax": 52235.95, "lymphome_probability": 0.8037210068222251}, {"annotation_id": "7b6aff71-439e-4ec6-b615-8afb25797823", "tile_id": "tile_7_1", "x": 7, "y": 1, "xmin": 35182.4, "ymin": 52235.95, "xmax": 35455.6, "ymax": 52473.9, "lymphome_probability": 0.7099749373307671}, {"annotation_id": "7b6aff71-439e-4ec6-b615-8afb25797823", "tile_id": "tile_7_2", "x": 7, "y": 2, "xmin": 35182.4, "ymin": 52473.9, "xmax": 35455.6, "ymax": 52711.85, "lymphome_probability": 0.7787621817042388}, {"annotation_id": "7b6aff71-439e-4ec6-b615-8afb25797823", "tile_id": "tile_7_3", "x": 7, "y": 3, "xmin": 35182.4, "ymin": 52711.85, "xmax": 35455.6, "ymax": 52949.8, "lymphome_probability": 0.04821087441853644}, {"annotation_id": "7b6aff71-439e-4ec6-b615-8afb25797823", "tile_id": "tile_7_4", "x": 7, "y": 4, "xmin": 35182.4, "ymin": 52949.8, "xmax": 35455.6, "ymax": 53187.75, "lymphome_probability": 0.4571227426200656}, {"annotation_id": "7b6aff71-439e-4ec6-b615-8afb25797823", "tile_id": "tile_7_5", "x": 7, "y": 5, "xmin": 35182.4, "ymin": 53187.75, "xmax": 35455.6, "ymax": 53425.7, "lymphome_probability": 0.14650658454717735}, {"annotation_id": "7b6aff71-439e-4ec6-b615-8afb25797823", "tile_id": "tile_7_6", "x": 7, "y": 6, "xmin": 35182.4, "ymin": 53425.7, "xmax": 35455.6, "ymax": 53663.65, "lymphome_probability": 0.09599010775700456}, {"annotation_id": "7b6aff71-439e-4ec6-b615-8afb25797823", "tile_id": "tile_7_7", "x": 7, "y": 7, "xmin": 35182.4, "ymin": 53663.65, "xmax": 35455.6, "ymax": 53901.6, "lymphome_probability": 0.6177609393874546}, {"annotation_id": "7b6aff71-439e-4ec6-b615-8afb25797823", "tile_id": "tile_7_8", "x": 7, "y": 8, "xmin": 35182.4, "ymin": 53901.6, "xmax": 35455.6, "ymax": 54139.55, "lymphome_probability": 0.06245600882543345}, {"annotation_id": "7b6aff71-439e-4ec6-b615-8afb25797823", "tile_id": "tile_7_9", "x": 7, "y": 9, "xmin": 35182.4, "ymin": 54139.55, "xmax": 35455.6, "ymax": 54377.5, "lymphome_probability": 0.14890264559722988}, {"annotation_id": "7b6aff71-439e-4ec6-b615-8afb25797823", "tile_id": "tile_7_10", "x": 7, "y": 10, "xmin": 35182.4, "ymin": 54377.5, "xmax": 35455.6, "ymax": 54615.45, "lymphome_probability": 0.946256973859925}, {"annotation_id": "7b6aff71-439e-4ec6-b615-8afb25797823", "tile_id": "tile_7_11", "x": 7, "y": 11, "xmin": 35182.4, "ymin": 54615.45, "xmax": 35455.6, "ymax": 54853.4, "lymphome_probability": 0.0036346621730533046}, {"annotation_id": "7b6aff71-439e-4ec6-b615-8afb25797823", "tile_id": "tile_7_12", "x": 7, "y": 12, "xmin": 35182.4, "ymin": 54853.4, "xmax": 35455.6, "ymax": 55091.35, "lymphome_probability": 0.3763313602019247}, {"annotation_id": "7b6aff71-439e-4ec6-b615-8afb25797823", "tile_id": "tile_7_13", "x": 7, "y": 13, "xmin": 35182.4, "ymin": 55091.35, "xmax": 35455.6, "ymax": 55329.3, "lymphome_probability": 0.9223890238814892}, {"annotation_id": "7b6aff71-439e-4ec6-b615-8afb25797823", "tile_id": "tile_7_14", "x": 7, "y": 14, "xmin": 35182.4, "ymin": 55329.3, "xmax": 35455.6, "ymax": 55567.25, "lymphome_probability": 0.9520687036781896}, {"annotation_id": "7b6aff71-439e-4ec6-b615-8afb25797823", "tile_id": "tile_7_15", "x": 7, "y": 15, "xmin": 35182.4, "ymin": 55567.25, "xmax": 35455.6, "ymax": 55805.2, "lymphome_probability": 0.5694540493352918}, {"annotation_id": "7b6aff71-439e-4ec6-b615-8afb25797823", "tile_id": "tile_7_16", "x": 7, "y": 16, "xmin": 35182.4, "ymin": 55805.2, "xmax": 35455.6, "ymax": 56043.15, "lymphome_probability": 0.8075641767764473}, {"annotation_id": "7b6aff71-439e-4ec6-b615-8afb25797823", "tile_id": "tile_7_17", "x": 7, "y": 17, "xmin": 35182.4, "ymin": 56043.15, "xmax": 35455.6, "ymax": 56281.1, "lymphome_probability": 0.6353037864848167}, {"annotation_id": "7b6aff71-439e-4ec6-b615-8afb25797823", "tile_id": "tile_7_18", "x": 7, "y": 18, "xmin": 35182.4, "ymin": 56281.1, "xmax": 35455.6, "ymax": 56519.05, "lymphome_probability": 0.1573798969489263}, {"annotation_id": "7b6aff71-439e-4ec6-b615-8afb25797823", "tile_id": "tile_7_19", "x": 7, "y": 19, "xmin": 35182.4, "ymin": 56519.05, "xmax": 35455.6, "ymax": 56757.0, "lymphome_probability": 0.05439481561225623}, {"annotation_id": "7b6aff71-439e-4ec6-b615-8afb25797823", "tile_id": "tile_8_0", "x": 8, "y": 0, "xmin": 35455.6, "ymin": 51998.0, "xmax": 35728.8, "ymax": 52235.95, "lymphome_probability": 0.957234030237188}, {"annotation_id": "7b6aff71-439e-4ec6-b615-8afb25797823", "tile_id": "tile_8_1", "x": 8, "y": 1, "xmin": 35455.6, "ymin": 52235.95, "xmax": 35728.8, "ymax": 52473.9, "lymphome_probability": 0.8583936927950947}, {"annotation_id": "7b6aff71-439e-4ec6-b615-8afb25797823", "tile_id": "tile_8_2", "x": 8, "y": 2, "xmin": 35455.6, "ymin": 52473.9, "xmax": 35728.8, "ymax": 52711.85, "lymphome_probability": 0.8331532243406041}, {"annotation_id": "7b6aff71-439e-4ec6-b615-8afb25797823", "tile_id": "tile_8_3", "x": 8, "y": 3, "xmin": 35455.6, "ymin": 52711.85, "xmax": 35728.8, "ymax": 52949.8, "lymphome_probability": 0.19210741938583265}, {"annotation_id": "7b6aff71-439e-4ec6-b615-8afb25797823", "tile_id": "tile_8_4", "x": 8, "y": 4, "xmin": 35455.6, "ymin": 52949.8, "xmax": 35728.8, "ymax": 53187.75, "lymphome_probability": 0.4465861959031554}, {"annotation_id": "7b6aff71-439e-4ec6-b615-8afb25797823", "tile_id": "tile_8_5", "x": 8, "y": 5, "xmin": 35455.6, "ymin": 53187.75, "xmax": 35728.8, "ymax": 53425.7, "lymphome_probability": 0.07313728659786489}, {"annotation_id": "7b6aff71-439e-4ec6-b615-8afb25797823", "tile_id": "tile_8_6", "x": 8, "y": 6, "xmin": 35455.6, "ymin": 53425.7, "xmax": 35728.8, "ymax": 53663.65, "lymphome_probability": 0.8223648808680085}, {"annotation_id": "7b6aff71-439e-4ec6-b615-8afb25797823", "tile_id": "tile_8_7", "x": 8, "y": 7, "xmin": 35455.6, "ymin": 53663.65, "xmax": 35728.8, "ymax": 53901.6, "lymphome_probability": 0.7842948600643103}, {"annotation_id": "7b6aff71-439e-4ec6-b615-8afb25797823", "tile_id": "tile_8_8", "x": 8, "y": 8, "xmin": 35455.6, "ymin": 53901.6, "xmax": 35728.8, "ymax": 54139.55, "lymphome_probability": 0.10690207379898553}, {"annotation_id": "7b6aff71-439e-4ec6-b615-8afb25797823", "tile_id": "tile_8_9", "x": 8, "y": 9, "xmin": 35455.6, "ymin": 54139.55, "xmax": 35728.8, "ymax": 54377.5, "lymphome_probability": 0.1834894774065794}, {"annotation_id": "7b6aff71-439e-4ec6-b615-8afb25797823", "tile_id": "tile_8_10", "x": 8, "y": 10, "xmin": 35455.6, "ymin": 54377.5, "xmax": 35728.8, "ymax": 54615.45, "lymphome_probability": 0.5838446680432219}, {"annotation_id": "7b6aff71-439e-4ec6-b615-8afb25797823", "tile_id": "tile_8_11", "x": 8, "y": 11, "xmin": 35455.6, "ymin": 54615.45, "xmax": 35728.8, "ymax": 54853.4, "lymphome_probability": 0.6165261334542582}, {"annotation_id": "7b6aff71-439e-4ec6-b615-8afb25797823", "tile_id": "tile_8_12", "x": 8, "y": 12, "xmin": 35455.6, "ymin": 54853.4, "xmax": 35728.8, "ymax": 55091.35, "lymphome_probability": 0.14282448563445116}, {"annotation_id": "7b6aff71-439e-4ec6-b615-8afb25797823", "tile_id": "tile_8_13", "x": 8, "y": 13, "xmin": 35455.6, "ymin": 55091.35, "xmax": 35728.8, "ymax": 55329.3, "lymphome_probability": 0.7758247009427865}, {"annotation_id": "7b6aff71-439e-4ec6-b615-8afb25797823", "tile_id": "tile_8_14", "x": 8, "y": 14, "xmin": 35455.6, "ymin": 55329.3, "xmax": 35728.8, "ymax": 55567.25, "lymphome_probability": 0.964355912284945}, {"annotation_id": "7b6aff71-439e-4ec6-b615-8afb25797823", "tile_id": "tile_8_15", "x": 8, "y": 15, "xmin": 35455.6, "ymin": 55567.25, "xmax": 35728.8, "ymax": 55805.2, "lymphome_probability": 0.3164847395710235}, {"annotation_id": "7b6aff71-439e-4ec6-b615-8afb25797823", "tile_id": "tile_8_16", "x": 8, "y": 16, "xmin": 35455.6, "ymin": 55805.2, "xmax": 35728.8, "ymax": 56043.15, "lymphome_probability": 0.6311709071553543}, {"annotation_id": "7b6aff71-439e-4ec6-b615-8afb25797823", "tile_id": "tile_8_17", "x": 8, "y": 17, "xmin": 35455.6, "ymin": 56043.15, "xmax": 35728.8, "ymax": 56281.1, "lymphome_probability": 0.5101160932264849}, {"annotation_id": "7b6aff71-439e-4ec6-b615-8afb25797823", "tile_id": "tile_8_18", "x": 8, "y": 18, "xmin": 35455.6, "ymin": 56281.1, "xmax": 35728.8, "ymax": 56519.05, "lymphome_probability": 0.6570888509381692}, {"annotation_id": "7b6aff71-439e-4ec6-b615-8afb25797823", "tile_id": "tile_8_19", "x": 8, "y": 19, "xmin": 35455.6, "ymin": 56519.05, "xmax": 35728.8, "ymax": 56757.0, "lymphome_probability": 0.39167613178887095}, {"annotation_id": "7b6aff71-439e-4ec6-b615-8afb25797823", "tile_id": "tile_9_0", "x": 9, "y": 0, "xmin": 35728.8, "ymin": 51998.0, "xmax": 36002.0, "ymax": 52235.95, "lymphome_probability": 0.8072904402375992}, {"annotation_id": "7b6aff71-439e-4ec6-b615-8afb25797823", "tile_id": "tile_9_1", "x": 9, "y": 1, "xmin": 35728.8, "ymin": 52235.95, "xmax": 36002.0, "ymax": 52473.9, "lymphome_probability": 0.36847731633218095}, {"annotation_id": "7b6aff71-439e-4ec6-b615-8afb25797823", "tile_id": "tile_9_2", "x": 9, "y": 2, "xmin": 35728.8, "ymin": 52473.9, "xmax": 36002.0, "ymax": 52711.85, "lymphome_probability": 0.6699910457323943}, {"annotation_id": "7b6aff71-439e-4ec6-b615-8afb25797823", "tile_id": "tile_9_3", "x": 9, "y": 3, "xmin": 35728.8, "ymin": 52711.85, "xmax": 36002.0, "ymax": 52949.8, "lymphome_probability": 0.17645559755556162}, {"annotation_id": "7b6aff71-439e-4ec6-b615-8afb25797823", "tile_id": "tile_9_4", "x": 9, "y": 4, "xmin": 35728.8, "ymin": 52949.8, "xmax": 36002.0, "ymax": 53187.75, "lymphome_probability": 0.6204422115012314}, {"annotation_id": "7b6aff71-439e-4ec6-b615-8afb25797823", "tile_id": "tile_9_5", "x": 9, "y": 5, "xmin": 35728.8, "ymin": 53187.75, "xmax": 36002.0, "ymax": 53425.7, "lymphome_probability": 0.24275855948874348}, {"annotation_id": "7b6aff71-439e-4ec6-b615-8afb25797823", "tile_id": "tile_9_6", "x": 9, "y": 6, "xmin": 35728.8, "ymin": 53425.7, "xmax": 36002.0, "ymax": 53663.65, "lymphome_probability": 0.3610495874858579}, {"annotation_id": "7b6aff71-439e-4ec6-b615-8afb25797823", "tile_id": "tile_9_7", "x": 9, "y": 7, "xmin": 35728.8, "ymin": 53663.65, "xmax": 36002.0, "ymax": 53901.6, "lymphome_probability": 0.5147343108042453}, {"annotation_id": "7b6aff71-439e-4ec6-b615-8afb25797823", "tile_id": "tile_9_8", "x": 9, "y": 8, "xmin": 35728.8, "ymin": 53901.6, "xmax": 36002.0, "ymax": 54139.55, "lymphome_probability": 0.03638408694203521}, {"annotation_id": "7b6aff71-439e-4ec6-b615-8afb25797823", "tile_id": "tile_9_9", "x": 9, "y": 9, "xmin": 35728.8, "ymin": 54139.55, "xmax": 36002.0, "ymax": 54377.5, "lymphome_probability": 0.2993767606753003}, {"annotation_id": "7b6aff71-439e-4ec6-b615-8afb25797823", "tile_id": "tile_9_10", "x": 9, "y": 10, "xmin": 35728.8, "ymin": 54377.5, "xmax": 36002.0, "ymax": 54615.45, "lymphome_probability": 0.935547699971763}, {"annotation_id": "7b6aff71-439e-4ec6-b615-8afb25797823", "tile_id": "tile_9_11", "x": 9, "y": 11, "xmin": 35728.8, "ymin": 54615.45, "xmax": 36002.0, "ymax": 54853.4, "lymphome_probability": 0.2308437267016773}, {"annotation_id": "7b6aff71-439e-4ec6-b615-8afb25797823", "tile_id": "tile_9_12", "x": 9, "y": 12, "xmin": 35728.8, "ymin": 54853.4, "xmax": 36002.0, "ymax": 55091.35, "lymphome_probability": 0.8165907907369715}, {"annotation_id": "7b6aff71-439e-4ec6-b615-8afb25797823", "tile_id": "tile_9_13", "x": 9, "y": 13, "xmin": 35728.8, "ymin": 55091.35, "xmax": 36002.0, "ymax": 55329.3, "lymphome_probability": 0.9734235075373252}, {"annotation_id": "7b6aff71-439e-4ec6-b615-8afb25797823", "tile_id": "tile_9_14", "x": 9, "y": 14, "xmin": 35728.8, "ymin": 55329.3, "xmax": 36002.0, "ymax": 55567.25, "lymphome_probability": 0.02473867781574557}, {"annotation_id": "7b6aff71-439e-4ec6-b615-8afb25797823", "tile_id": "tile_9_15", "x": 9, "y": 15, "xmin": 35728.8, "ymin": 55567.25, "xmax": 36002.0, "ymax": 55805.2, "lymphome_probability": 0.8369914120334847}, {"annotation_id": "7b6aff71-439e-4ec6-b615-8afb25797823", "tile_id": "tile_9_16", "x": 9, "y": 16, "xmin": 35728.8, "ymin": 55805.2, "xmax": 36002.0, "ymax": 56043.15, "lymphome_probability": 0.5997096287660837}, {"annotation_id": "7b6aff71-439e-4ec6-b615-8afb25797823", "tile_id": "tile_9_17", "x": 9, "y": 17, "xmin": 35728.8, "ymin": 56043.15, "xmax": 36002.0, "ymax": 56281.1, "lymphome_probability": 0.9774278367317195}, {"annotation_id": "7b6aff71-439e-4ec6-b615-8afb25797823", "tile_id": "tile_9_18", "x": 9, "y": 18, "xmin": 35728.8, "ymin": 56281.1, "xmax": 36002.0, "ymax": 56519.05, "lymphome_probability": 0.35134467327666286}, {"annotation_id": "7b6aff71-439e-4ec6-b615-8afb25797823", "tile_id": "tile_9_19", "x": 9, "y": 19, "xmin": 35728.8, "ymin": 56519.05, "xmax": 36002.0, "ymax": 56757.0, "lymphome_probability": 0.3711506726499689}, {"annotation_id": "7b6aff71-439e-4ec6-b615-8afb25797823", "tile_id": "tile_10_0", "x": 10, "y": 0, "xmin": 36002.0, "ymin": 51998.0, "xmax": 36275.2, "ymax": 52235.95, "lymphome_probability": 0.7073499230018133}, {"annotation_id": "7b6aff71-439e-4ec6-b615-8afb25797823", "tile_id": "tile_10_1", "x": 10, "y": 1, "xmin": 36002.0, "ymin": 52235.95, "xmax": 36275.2, "ymax": 52473.9, "lymphome_probability": 0.006631865161918493}, {"annotation_id": "7b6aff71-439e-4ec6-b615-8afb25797823", "tile_id": "tile_10_2", "x": 10, "y": 2, "xmin": 36002.0, "ymin": 52473.9, "xmax": 36275.2, "ymax": 52711.85, "lymphome_probability": 0.056403193858745815}, {"annotation_id": "7b6aff71-439e-4ec6-b615-8afb25797823", "tile_id": "tile_10_3", "x": 10, "y": 3, "xmin": 36002.0, "ymin": 52711.85, "xmax": 36275.2, "ymax": 52949.8, "lymphome_probability": 0.8515967978044785}, {"annotation_id": "7b6aff71-439e-4ec6-b615-8afb25797823", "tile_id": "tile_10_4", "x": 10, "y": 4, "xmin": 36002.0, "ymin": 52949.8, "xmax": 36275.2, "ymax": 53187.75, "lymphome_probability": 0.7808592849448247}, {"annotation_id": "7b6aff71-439e-4ec6-b615-8afb25797823", "tile_id": "tile_10_5", "x": 10, "y": 5, "xmin": 36002.0, "ymin": 53187.75, "xmax": 36275.2, "ymax": 53425.7, "lymphome_probability": 0.4102745239549922}, {"annotation_id": "7b6aff71-439e-4ec6-b615-8afb25797823", "tile_id": "tile_10_6", "x": 10, "y": 6, "xmin": 36002.0, "ymin": 53425.7, "xmax": 36275.2, "ymax": 53663.65, "lymphome_probability": 0.5366382381178061}, {"annotation_id": "7b6aff71-439e-4ec6-b615-8afb25797823", "tile_id": "tile_10_7", "x": 10, "y": 7, "xmin": 36002.0, "ymin": 53663.65, "xmax": 36275.2, "ymax": 53901.6, "lymphome_probability": 0.8915231493209297}, {"annotation_id": "7b6aff71-439e-4ec6-b615-8afb25797823", "tile_id": "tile_10_8", "x": 10, "y": 8, "xmin": 36002.0, "ymin": 53901.6, "xmax": 36275.2, "ymax": 54139.55, "lymphome_probability": 0.5422533879984953}, {"annotation_id": "7b6aff71-439e-4ec6-b615-8afb25797823", "tile_id": "tile_10_9", "x": 10, "y": 9, "xmin": 36002.0, "ymin": 54139.55, "xmax": 36275.2, "ymax": 54377.5, "lymphome_probability": 0.664765970651852}, {"annotation_id": "7b6aff71-439e-4ec6-b615-8afb25797823", "tile_id": "tile_10_10", "x": 10, "y": 10, "xmin": 36002.0, "ymin": 54377.5, "xmax": 36275.2, "ymax": 54615.45, "lymphome_probability": 0.5804784312502312}, {"annotation_id": "7b6aff71-439e-4ec6-b615-8afb25797823", "tile_id": "tile_10_11", "x": 10, "y": 11, "xmin": 36002.0, "ymin": 54615.45, "xmax": 36275.2, "ymax": 54853.4, "lymphome_probability": 0.820365336262059}, {"annotation_id": "7b6aff71-439e-4ec6-b615-8afb25797823", "tile_id": "tile_10_12", "x": 10, "y": 12, "xmin": 36002.0, "ymin": 54853.4, "xmax": 36275.2, "ymax": 55091.35, "lymphome_probability": 0.650601847152867}, {"annotation_id": "7b6aff71-439e-4ec6-b615-8afb25797823", "tile_id": "tile_10_13", "x": 10, "y": 13, "xmin": 36002.0, "ymin": 55091.35, "xmax": 36275.2, "ymax": 55329.3, "lymphome_probability": 0.5307926446224374}, {"annotation_id": "7b6aff71-439e-4ec6-b615-8afb25797823", "tile_id": "tile_10_14", "x": 10, "y": 14, "xmin": 36002.0, "ymin": 55329.3, "xmax": 36275.2, "ymax": 55567.25, "lymphome_probability": 0.0069405642074744645}, {"annotation_id": "7b6aff71-439e-4ec6-b615-8afb25797823", "tile_id": "tile_10_15", "x": 10, "y": 15, "xmin": 36002.0, "ymin": 55567.25, "xmax": 36275.2, "ymax": 55805.2, "lymphome_probability": 0.7187710790811342}, {"annotation_id": "7b6aff71-439e-4ec6-b615-8afb25797823", "tile_id": "tile_10_16", "x": 10, "y": 16, "xmin": 36002.0, "ymin": 55805.2, "xmax": 36275.2, "ymax": 56043.15, "lymphome_probability": 0.20416448974923462}, {"annotation_id": "7b6aff71-439e-4ec6-b615-8afb25797823", "tile_id": "tile_10_17", "x": 10, "y": 17, "xmin": 36002.0, "ymin": 56043.15, "xmax": 36275.2, "ymax": 56281.1, "lymphome_probability": 0.7014324043520508}, {"annotation_id": "7b6aff71-439e-4ec6-b615-8afb25797823", "tile_id": "tile_10_18", "x": 10, "y": 18, "xmin": 36002.0, "ymin": 56281.1, "xmax": 36275.2, "ymax": 56519.05, "lymphome_probability": 0.38780992815692605}, {"annotation_id": "7b6aff71-439e-4ec6-b615-8afb25797823", "tile_id": "tile_10_19", "x": 10, "y": 19, "xmin": 36002.0, "ymin": 56519.05, "xmax": 36275.2, "ymax": 56757.0, "lymphome_probability": 0.5782438689043523}, {"annotation_id": "7b6aff71-439e-4ec6-b615-8afb25797823", "tile_id": "tile_11_0", "x": 11, "y": 0, "xmin": 36275.2, "ymin": 51998.0, "xmax": 36548.4, "ymax": 52235.95, "lymphome_probability": 0.921061843538041}, {"annotation_id": "7b6aff71-439e-4ec6-b615-8afb25797823", "tile_id": "tile_11_1", "x": 11, "y": 1, "xmin": 36275.2, "ymin": 52235.95, "xmax": 36548.4, "ymax": 52473.9, "lymphome_probability": 0.08084355167249158}, {"annotation_id": "7b6aff71-439e-4ec6-b615-8afb25797823", "tile_id": "tile_11_2", "x": 11, "y": 2, "xmin": 36275.2, "ymin": 52473.9, "xmax": 36548.4, "ymax": 52711.85, "lymphome_probability": 0.8557270024002624}, {"annotation_id": "7b6aff71-439e-4ec6-b615-8afb25797823", "tile_id": "tile_11_3", "x": 11, "y": 3, "xmin": 36275.2, "ymin": 52711.85, "xmax": 36548.4, "ymax": 52949.8, "lymphome_probability": 0.09579359021575995}, {"annotation_id": "7b6aff71-439e-4ec6-b615-8afb25797823", "tile_id": "tile_11_4", "x": 11, "y": 4, "xmin": 36275.2, "ymin": 52949.8, "xmax": 36548.4, "ymax": 53187.75, "lymphome_probability": 0.5138820567840906}, {"annotation_id": "7b6aff71-439e-4ec6-b615-8afb25797823", "tile_id": "tile_11_5", "x": 11, "y": 5, "xmin": 36275.2, "ymin": 53187.75, "xmax": 36548.4, "ymax": 53425.7, "lymphome_probability": 0.45847420672564076}, {"annotation_id": "7b6aff71-439e-4ec6-b615-8afb25797823", "tile_id": "tile_11_6", "x": 11, "y": 6, "xmin": 36275.2, "ymin": 53425.7, "xmax": 36548.4, "ymax": 53663.65, "lymphome_probability": 0.1671959332413806}, {"annotation_id": "7b6aff71-439e-4ec6-b615-8afb25797823", "tile_id": "tile_11_7", "x": 11, "y": 7, "xmin": 36275.2, "ymin": 53663.65, "xmax": 36548.4, "ymax": 53901.6, "lymphome_probability": 0.030614284938651593}, {"annotation_id": "7b6aff71-439e-4ec6-b615-8afb25797823", "tile_id": "tile_11_8", "x": 11, "y": 8, "xmin": 36275.2, "ymin": 53901.6, "xmax": 36548.4, "ymax": 54139.55, "lymphome_probability": 0.05849056135443775}, {"annotation_id": "7b6aff71-439e-4ec6-b615-8afb25797823", "tile_id": "tile_11_9", "x": 11, "y": 9, "xmin": 36275.2, "ymin": 54139.55, "xmax": 36548.4, "ymax": 54377.5, "lymphome_probability": 0.5448888971965425}, {"annotation_id": "7b6aff71-439e-4ec6-b615-8afb25797823", "tile_id": "tile_11_10", "x": 11, "y": 10, "xmin": 36275.2, "ymin": 54377.5, "xmax": 36548.4, "ymax": 54615.45, "lymphome_probability": 0.8627044276301733}, {"annotation_id": "7b6aff71-439e-4ec6-b615-8afb25797823", "tile_id": "tile_11_11", "x": 11, "y": 11, "xmin": 36275.2, "ymin": 54615.45, "xmax": 36548.4, "ymax": 54853.4, "lymphome_probability": 0.7546849968973363}, {"annotation_id": "7b6aff71-439e-4ec6-b615-8afb25797823", "tile_id": "tile_11_12", "x": 11, "y": 12, "xmin": 36275.2, "ymin": 54853.4, "xmax": 36548.4, "ymax": 55091.35, "lymphome_probability": 0.0025243266618327764}, {"annotation_id": "7b6aff71-439e-4ec6-b615-8afb25797823", "tile_id": "tile_11_13", "x": 11, "y": 13, "xmin": 36275.2, "ymin": 55091.35, "xmax": 36548.4, "ymax": 55329.3, "lymphome_probability": 0.611849088685043}, {"annotation_id": "7b6aff71-439e-4ec6-b615-8afb25797823", "tile_id": "tile_11_14", "x": 11, "y": 14, "xmin": 36275.2, "ymin": 55329.3, "xmax": 36548.4, "ymax": 55567.25, "lymphome_probability": 0.6224570487849859}, {"annotation_id": "7b6aff71-439e-4ec6-b615-8afb25797823", "tile_id": "tile_11_15", "x": 11, "y": 15, "xmin": 36275.2, "ymin": 55567.25, "xmax": 36548.4, "ymax": 55805.2, "lymphome_probability": 0.022349584334206307}, {"annotation_id": "7b6aff71-439e-4ec6-b615-8afb25797823", "tile_id": "tile_11_16", "x": 11, "y": 16, "xmin": 36275.2, "ymin": 55805.2, "xmax": 36548.4, "ymax": 56043.15, "lymphome_probability": 0.329456975599441}, {"annotation_id": "7b6aff71-439e-4ec6-b615-8afb25797823", "tile_id": "tile_11_17", "x": 11, "y": 17, "xmin": 36275.2, "ymin": 56043.15, "xmax": 36548.4, "ymax": 56281.1, "lymphome_probability": 0.1581677529310117}, {"annotation_id": "7b6aff71-439e-4ec6-b615-8afb25797823", "tile_id": "tile_11_18", "x": 11, "y": 18, "xmin": 36275.2, "ymin": 56281.1, "xmax": 36548.4, "ymax": 56519.05, "lymphome_probability": 0.8053376712979037}, {"annotation_id": "7b6aff71-439e-4ec6-b615-8afb25797823", "tile_id": "tile_11_19", "x": 11, "y": 19, "xmin": 36275.2, "ymin": 56519.05, "xmax": 36548.4, "ymax": 56757.0, "lymphome_probability": 0.9065673491891237}, {"annotation_id": "7b6aff71-439e-4ec6-b615-8afb25797823", "tile_id": "tile_12_0", "x": 12, "y": 0, "xmin": 36548.4, "ymin": 51998.0, "xmax": 36821.6, "ymax": 52235.95, "lymphome_probability": 0.24555474406361832}, {"annotation_id": "7b6aff71-439e-4ec6-b615-8afb25797823", "tile_id": "tile_12_1", "x": 12, "y": 1, "xmin": 36548.4, "ymin": 52235.95, "xmax": 36821.6, "ymax": 52473.9, "lymphome_probability": 0.3795983244258282}, {"annotation_id": "7b6aff71-439e-4ec6-b615-8afb25797823", "tile_id": "tile_12_2", "x": 12, "y": 2, "xmin": 36548.4, "ymin": 52473.9, "xmax": 36821.6, "ymax": 52711.85, "lymphome_probability": 0.04743299456673389}, {"annotation_id": "7b6aff71-439e-4ec6-b615-8afb25797823", "tile_id": "tile_12_3", "x": 12, "y": 3, "xmin": 36548.4, "ymin": 52711.85, "xmax": 36821.6, "ymax": 52949.8, "lymphome_probability": 0.45349518305136416}, {"annotation_id": "7b6aff71-439e-4ec6-b615-8afb25797823", "tile_id": "tile_12_4", "x": 12, "y": 4, "xmin": 36548.4, "ymin": 52949.8, "xmax": 36821.6, "ymax": 53187.75, "lymphome_probability": 0.9158981760175299}, {"annotation_id": "7b6aff71-439e-4ec6-b615-8afb25797823", "tile_id": "tile_12_5", "x": 12, "y": 5, "xmin": 36548.4, "ymin": 53187.75, "xmax": 36821.6, "ymax": 53425.7, "lymphome_probability": 0.005105567644272835}, {"annotation_id": "7b6aff71-439e-4ec6-b615-8afb25797823", "tile_id": "tile_12_6", "x": 12, "y": 6, "xmin": 36548.4, "ymin": 53425.7, "xmax": 36821.6, "ymax": 53663.65, "lymphome_probability": 0.9846937048059631}, {"annotation_id": "7b6aff71-439e-4ec6-b615-8afb25797823", "tile_id": "tile_12_7", "x": 12, "y": 7, "xmin": 36548.4, "ymin": 53663.65, "xmax": 36821.6, "ymax": 53901.6, "lymphome_probability": 0.9883275938939398}, {"annotation_id": "7b6aff71-439e-4ec6-b615-8afb25797823", "tile_id": "tile_12_8", "x": 12, "y": 8, "xmin": 36548.4, "ymin": 53901.6, "xmax": 36821.6, "ymax": 54139.55, "lymphome_probability": 0.9100248617342765}, {"annotation_id": "7b6aff71-439e-4ec6-b615-8afb25797823", "tile_id": "tile_12_9", "x": 12, "y": 9, "xmin": 36548.4, "ymin": 54139.55, "xmax": 36821.6, "ymax": 54377.5, "lymphome_probability": 0.4088150431337184}, {"annotation_id": "7b6aff71-439e-4ec6-b615-8afb25797823", "tile_id": "tile_12_10", "x": 12, "y": 10, "xmin": 36548.4, "ymin": 54377.5, "xmax": 36821.6, "ymax": 54615.45, "lymphome_probability": 0.05522602669612098}, {"annotation_id": "7b6aff71-439e-4ec6-b615-8afb25797823", "tile_id": "tile_12_11", "x": 12, "y": 11, "xmin": 36548.4, "ymin": 54615.45, "xmax": 36821.6, "ymax": 54853.4, "lymphome_probability": 0.4306573267363146}, {"annotation_id": "7b6aff71-439e-4ec6-b615-8afb25797823", "tile_id": "tile_12_12", "x": 12, "y": 12, "xmin": 36548.4, "ymin": 54853.4, "xmax": 36821.6, "ymax": 55091.35, "lymphome_probability": 0.9609241794602932}, {"annotation_id": "7b6aff71-439e-4ec6-b615-8afb25797823", "tile_id": "tile_12_13", "x": 12, "y": 13, "xmin": 36548.4, "ymin": 55091.35, "xmax": 36821.6, "ymax": 55329.3, "lymphome_probability": 0.12896365041207092}, {"annotation_id": "7b6aff71-439e-4ec6-b615-8afb25797823", "tile_id": "tile_12_14", "x": 12, "y": 14, "xmin": 36548.4, "ymin": 55329.3, "xmax": 36821.6, "ymax": 55567.25, "lymphome_probability": 0.6730703168476747}, {"annotation_id": "7b6aff71-439e-4ec6-b615-8afb25797823", "tile_id": "tile_12_15", "x": 12, "y": 15, "xmin": 36548.4, "ymin": 55567.25, "xmax": 36821.6, "ymax": 55805.2, "lymphome_probability": 0.6782011962767974}, {"annotation_id": "7b6aff71-439e-4ec6-b615-8afb25797823", "tile_id": "tile_12_16", "x": 12, "y": 16, "xmin": 36548.4, "ymin": 55805.2, "xmax": 36821.6, "ymax": 56043.15, "lymphome_probability": 0.049300724559855236}, {"annotation_id": "7b6aff71-439e-4ec6-b615-8afb25797823", "tile_id": "tile_12_17", "x": 12, "y": 17, "xmin": 36548.4, "ymin": 56043.15, "xmax": 36821.6, "ymax": 56281.1, "lymphome_probability": 0.5500018403188597}, {"annotation_id": "7b6aff71-439e-4ec6-b615-8afb25797823", "tile_id": "tile_12_18", "x": 12, "y": 18, "xmin": 36548.4, "ymin": 56281.1, "xmax": 36821.6, "ymax": 56519.05, "lymphome_probability": 0.513688496218606}, {"annotation_id": "7b6aff71-439e-4ec6-b615-8afb25797823", "tile_id": "tile_12_19", "x": 12, "y": 19, "xmin": 36548.4, "ymin": 56519.05, "xmax": 36821.6, "ymax": 56757.0, "lymphome_probability": 0.890593974151899}, {"annotation_id": "7b6aff71-439e-4ec6-b615-8afb25797823", "tile_id": "tile_13_0", "x": 13, "y": 0, "xmin": 36821.6, "ymin": 51998.0, "xmax": 37094.8, "ymax": 52235.95, "lymphome_probability": 0.512833771555286}, {"annotation_id": "7b6aff71-439e-4ec6-b615-8afb25797823", "tile_id": "tile_13_1", "x": 13, "y": 1, "xmin": 36821.6, "ymin": 52235.95, "xmax": 37094.8, "ymax": 52473.9, "lymphome_probability": 0.19309536440553088}, {"annotation_id": "7b6aff71-439e-4ec6-b615-8afb25797823", "tile_id": "tile_13_2", "x": 13, "y": 2, "xmin": 36821.6, "ymin": 52473.9, "xmax": 37094.8, "ymax": 52711.85, "lymphome_probability": 0.3404455422369489}, {"annotation_id": "7b6aff71-439e-4ec6-b615-8afb25797823", "tile_id": "tile_13_3", "x": 13, "y": 3, "xmin": 36821.6, "ymin": 52711.85, "xmax": 37094.8, "ymax": 52949.8, "lymphome_probability": 0.9518668319097034}, {"annotation_id": "7b6aff71-439e-4ec6-b615-8afb25797823", "tile_id": "tile_13_4", "x": 13, "y": 4, "xmin": 36821.6, "ymin": 52949.8, "xmax": 37094.8, "ymax": 53187.75, "lymphome_probability": 0.8624830766341068}, {"annotation_id": "7b6aff71-439e-4ec6-b615-8afb25797823", "tile_id": "tile_13_5", "x": 13, "y": 5, "xmin": 36821.6, "ymin": 53187.75, "xmax": 37094.8, "ymax": 53425.7, "lymphome_probability": 0.140457423085253}, {"annotation_id": "7b6aff71-439e-4ec6-b615-8afb25797823", "tile_id": "tile_13_6", "x": 13, "y": 6, "xmin": 36821.6, "ymin": 53425.7, "xmax": 37094.8, "ymax": 53663.65, "lymphome_probability": 0.7997531068736244}, {"annotation_id": "7b6aff71-439e-4ec6-b615-8afb25797823", "tile_id": "tile_13_7", "x": 13, "y": 7, "xmin": 36821.6, "ymin": 53663.65, "xmax": 37094.8, "ymax": 53901.6, "lymphome_probability": 0.27383079976685676}, {"annotation_id": "7b6aff71-439e-4ec6-b615-8afb25797823", "tile_id": "tile_13_8", "x": 13, "y": 8, "xmin": 36821.6, "ymin": 53901.6, "xmax": 37094.8, "ymax": 54139.55, "lymphome_probability": 0.8718436037334082}, {"annotation_id": "7b6aff71-439e-4ec6-b615-8afb25797823", "tile_id": "tile_13_9", "x": 13, "y": 9, "xmin": 36821.6, "ymin": 54139.55, "xmax": 37094.8, "ymax": 54377.5, "lymphome_probability": 0.9282210276566907}, {"annotation_id": "7b6aff71-439e-4ec6-b615-8afb25797823", "tile_id": "tile_13_10", "x": 13, "y": 10, "xmin": 36821.6, "ymin": 54377.5, "xmax": 37094.8, "ymax": 54615.45, "lymphome_probability": 0.9867233938376854}, {"annotation_id": "7b6aff71-439e-4ec6-b615-8afb25797823", "tile_id": "tile_13_11", "x": 13, "y": 11, "xmin": 36821.6, "ymin": 54615.45, "xmax": 37094.8, "ymax": 54853.4, "lymphome_probability": 0.469008744276444}, {"annotation_id": "7b6aff71-439e-4ec6-b615-8afb25797823", "tile_id": "tile_13_12", "x": 13, "y": 12, "xmin": 36821.6, "ymin": 54853.4, "xmax": 37094.8, "ymax": 55091.35, "lymphome_probability": 0.5674672546543263}, {"annotation_id": "7b6aff71-439e-4ec6-b615-8afb25797823", "tile_id": "tile_13_13", "x": 13, "y": 13, "xmin": 36821.6, "ymin": 55091.35, "xmax": 37094.8, "ymax": 55329.3, "lymphome_probability": 0.6064927857678301}, {"annotation_id": "7b6aff71-439e-4ec6-b615-8afb25797823", "tile_id": "tile_13_14", "x": 13, "y": 14, "xmin": 36821.6, "ymin": 55329.3, "xmax": 37094.8, "ymax": 55567.25, "lymphome_probability": 0.6238838875214822}, {"annotation_id": "7b6aff71-439e-4ec6-b615-8afb25797823", "tile_id": "tile_13_15", "x": 13, "y": 15, "xmin": 36821.6, "ymin": 55567.25, "xmax": 37094.8, "ymax": 55805.2, "lymphome_probability": 0.3957574872082176}, {"annotation_id": "7b6aff71-439e-4ec6-b615-8afb25797823", "tile_id": "tile_13_16", "x": 13, "y": 16, "xmin": 36821.6, "ymin": 55805.2, "xmax": 37094.8, "ymax": 56043.15, "lymphome_probability": 0.07669706478685645}, {"annotation_id": "7b6aff71-439e-4ec6-b615-8afb25797823", "tile_id": "tile_13_17", "x": 13, "y": 17, "xmin": 36821.6, "ymin": 56043.15, "xmax": 37094.8, "ymax": 56281.1, "lymphome_probability": 0.020248274949489442}, {"annotation_id": "7b6aff71-439e-4ec6-b615-8afb25797823", "tile_id": "tile_13_18", "x": 13, "y": 18, "xmin": 36821.6, "ymin": 56281.1, "xmax": 37094.8, "ymax": 56519.05, "lymphome_probability": 0.492794507228155}, {"annotation_id": "7b6aff71-439e-4ec6-b615-8afb25797823", "tile_id": "tile_13_19", "x": 13, "y": 19, "xmin": 36821.6, "ymin": 56519.05, "xmax": 37094.8, "ymax": 56757.0, "lymphome_probability": 0.6553625698752289}, {"annotation_id": "7b6aff71-439e-4ec6-b615-8afb25797823", "tile_id": "tile_14_0", "x": 14, "y": 0, "xmin": 37094.8, "ymin": 51998.0, "xmax": 37368.0, "ymax": 52235.95, "lymphome_probability": 0.5407332832317858}, {"annotation_id": "7b6aff71-439e-4ec6-b615-8afb25797823", "tile_id": "tile_14_1", "x": 14, "y": 1, "xmin": 37094.8, "ymin": 52235.95, "xmax": 37368.0, "ymax": 52473.9, "lymphome_probability": 0.01796794591167994}, {"annotation_id": "7b6aff71-439e-4ec6-b615-8afb25797823", "tile_id": "tile_14_2", "x": 14, "y": 2, "xmin": 37094.8, "ymin": 52473.9, "xmax": 37368.0, "ymax": 52711.85, "lymphome_probability": 0.5566708805921273}, {"annotation_id": "7b6aff71-439e-4ec6-b615-8afb25797823", "tile_id": "tile_14_3", "x": 14, "y": 3, "xmin": 37094.8, "ymin": 52711.85, "xmax": 37368.0, "ymax": 52949.8, "lymphome_probability": 0.19675872276652773}, {"annotation_id": "7b6aff71-439e-4ec6-b615-8afb25797823", "tile_id": "tile_14_4", "x": 14, "y": 4, "xmin": 37094.8, "ymin": 52949.8, "xmax": 37368.0, "ymax": 53187.75, "lymphome_probability": 0.08079736698428686}, {"annotation_id": "7b6aff71-439e-4ec6-b615-8afb25797823", "tile_id": "tile_14_5", "x": 14, "y": 5, "xmin": 37094.8, "ymin": 53187.75, "xmax": 37368.0, "ymax": 53425.7, "lymphome_probability": 0.550549435734114}, {"annotation_id": "7b6aff71-439e-4ec6-b615-8afb25797823", "tile_id": "tile_14_6", "x": 14, "y": 6, "xmin": 37094.8, "ymin": 53425.7, "xmax": 37368.0, "ymax": 53663.65, "lymphome_probability": 0.5277285907748657}, {"annotation_id": "7b6aff71-439e-4ec6-b615-8afb25797823", "tile_id": "tile_14_7", "x": 14, "y": 7, "xmin": 37094.8, "ymin": 53663.65, "xmax": 37368.0, "ymax": 53901.6, "lymphome_probability": 0.049244815427054056}, {"annotation_id": "7b6aff71-439e-4ec6-b615-8afb25797823", "tile_id": "tile_14_8", "x": 14, "y": 8, "xmin": 37094.8, "ymin": 53901.6, "xmax": 37368.0, "ymax": 54139.55, "lymphome_probability": 0.5102281972594708}, {"annotation_id": "7b6aff71-439e-4ec6-b615-8afb25797823", "tile_id": "tile_14_9", "x": 14, "y": 9, "xmin": 37094.8, "ymin": 54139.55, "xmax": 37368.0, "ymax": 54377.5, "lymphome_probability": 0.789545530750948}, {"annotation_id": "7b6aff71-439e-4ec6-b615-8afb25797823", "tile_id": "tile_14_10", "x": 14, "y": 10, "xmin": 37094.8, "ymin": 54377.5, "xmax": 37368.0, "ymax": 54615.45, "lymphome_probability": 0.5796531402463774}, {"annotation_id": "7b6aff71-439e-4ec6-b615-8afb25797823", "tile_id": "tile_14_11", "x": 14, "y": 11, "xmin": 37094.8, "ymin": 54615.45, "xmax": 37368.0, "ymax": 54853.4, "lymphome_probability": 0.5257513317082818}, {"annotation_id": "7b6aff71-439e-4ec6-b615-8afb25797823", "tile_id": "tile_14_12", "x": 14, "y": 12, "xmin": 37094.8, "ymin": 54853.4, "xmax": 37368.0, "ymax": 55091.35, "lymphome_probability": 0.9389407833816266}, {"annotation_id": "7b6aff71-439e-4ec6-b615-8afb25797823", "tile_id": "tile_14_13", "x": 14, "y": 13, "xmin": 37094.8, "ymin": 55091.35, "xmax": 37368.0, "ymax": 55329.3, "lymphome_probability": 0.7802994746058811}, {"annotation_id": "7b6aff71-439e-4ec6-b615-8afb25797823", "tile_id": "tile_14_14", "x": 14, "y": 14, "xmin": 37094.8, "ymin": 55329.3, "xmax": 37368.0, "ymax": 55567.25, "lymphome_probability": 0.9978913263309087}, {"annotation_id": "7b6aff71-439e-4ec6-b615-8afb25797823", "tile_id": "tile_14_15", "x": 14, "y": 15, "xmin": 37094.8, "ymin": 55567.25, "xmax": 37368.0, "ymax": 55805.2, "lymphome_probability": 0.8145752679365071}, {"annotation_id": "7b6aff71-439e-4ec6-b615-8afb25797823", "tile_id": "tile_14_16", "x": 14, "y": 16, "xmin": 37094.8, "ymin": 55805.2, "xmax": 37368.0, "ymax": 56043.15, "lymphome_probability": 0.5986753013469704}, {"annotation_id": "7b6aff71-439e-4ec6-b615-8afb25797823", "tile_id": "tile_14_17", "x": 14, "y": 17, "xmin": 37094.8, "ymin": 56043.15, "xmax": 37368.0, "ymax": 56281.1, "lymphome_probability": 0.7155889208631823}, {"annotation_id": "7b6aff71-439e-4ec6-b615-8afb25797823", "tile_id": "tile_14_18", "x": 14, "y": 18, "xmin": 37094.8, "ymin": 56281.1, "xmax": 37368.0, "ymax": 56519.05, "lymphome_probability": 0.5376441264113644}, {"annotation_id": "7b6aff71-439e-4ec6-b615-8afb25797823", "tile_id": "tile_14_19", "x": 14, "y": 19, "xmin": 37094.8, "ymin": 56519.05, "xmax": 37368.0, "ymax": 56757.0, "lymphome_probability": 0.6964440202827418}, {"annotation_id": "7b6aff71-439e-4ec6-b615-8afb25797823", "tile_id": "tile_15_0", "x": 15, "y": 0, "xmin": 37368.0, "ymin": 51998.0, "xmax": 37641.2, "ymax": 52235.95, "lymphome_probability": 0.8072196147215066}, {"annotation_id": "7b6aff71-439e-4ec6-b615-8afb25797823", "tile_id": "tile_15_1", "x": 15, "y": 1, "xmin": 37368.0, "ymin": 52235.95, "xmax": 37641.2, "ymax": 52473.9, "lymphome_probability": 0.8450583268625013}, {"annotation_id": "7b6aff71-439e-4ec6-b615-8afb25797823", "tile_id": "tile_15_2", "x": 15, "y": 2, "xmin": 37368.0, "ymin": 52473.9, "xmax": 37641.2, "ymax": 52711.85, "lymphome_probability": 0.783002312187045}, {"annotation_id": "7b6aff71-439e-4ec6-b615-8afb25797823", "tile_id": "tile_15_3", "x": 15, "y": 3, "xmin": 37368.0, "ymin": 52711.85, "xmax": 37641.2, "ymax": 52949.8, "lymphome_probability": 0.784487940698111}, {"annotation_id": "7b6aff71-439e-4ec6-b615-8afb25797823", "tile_id": "tile_15_4", "x": 15, "y": 4, "xmin": 37368.0, "ymin": 52949.8, "xmax": 37641.2, "ymax": 53187.75, "lymphome_probability": 0.30898290050384825}, {"annotation_id": "7b6aff71-439e-4ec6-b615-8afb25797823", "tile_id": "tile_15_5", "x": 15, "y": 5, "xmin": 37368.0, "ymin": 53187.75, "xmax": 37641.2, "ymax": 53425.7, "lymphome_probability": 0.6883610278014539}, {"annotation_id": "7b6aff71-439e-4ec6-b615-8afb25797823", "tile_id": "tile_15_6", "x": 15, "y": 6, "xmin": 37368.0, "ymin": 53425.7, "xmax": 37641.2, "ymax": 53663.65, "lymphome_probability": 0.10504568113399049}, {"annotation_id": "7b6aff71-439e-4ec6-b615-8afb25797823", "tile_id": "tile_15_7", "x": 15, "y": 7, "xmin": 37368.0, "ymin": 53663.65, "xmax": 37641.2, "ymax": 53901.6, "lymphome_probability": 0.35571092708616225}, {"annotation_id": "7b6aff71-439e-4ec6-b615-8afb25797823", "tile_id": "tile_15_8", "x": 15, "y": 8, "xmin": 37368.0, "ymin": 53901.6, "xmax": 37641.2, "ymax": 54139.55, "lymphome_probability": 0.07583036811804678}, {"annotation_id": "7b6aff71-439e-4ec6-b615-8afb25797823", "tile_id": "tile_15_9", "x": 15, "y": 9, "xmin": 37368.0, "ymin": 54139.55, "xmax": 37641.2, "ymax": 54377.5, "lymphome_probability": 0.3006424136641569}, {"annotation_id": "7b6aff71-439e-4ec6-b615-8afb25797823", "tile_id": "tile_15_10", "x": 15, "y": 10, "xmin": 37368.0, "ymin": 54377.5, "xmax": 37641.2, "ymax": 54615.45, "lymphome_probability": 0.49351702783274676}, {"annotation_id": "7b6aff71-439e-4ec6-b615-8afb25797823", "tile_id": "tile_15_11", "x": 15, "y": 11, "xmin": 37368.0, "ymin": 54615.45, "xmax": 37641.2, "ymax": 54853.4, "lymphome_probability": 0.5360022420775591}, {"annotation_id": "7b6aff71-439e-4ec6-b615-8afb25797823", "tile_id": "tile_15_12", "x": 15, "y": 12, "xmin": 37368.0, "ymin": 54853.4, "xmax": 37641.2, "ymax": 55091.35, "lymphome_probability": 0.023827527655507552}, {"annotation_id": "7b6aff71-439e-4ec6-b615-8afb25797823", "tile_id": "tile_15_13", "x": 15, "y": 13, "xmin": 37368.0, "ymin": 55091.35, "xmax": 37641.2, "ymax": 55329.3, "lymphome_probability": 0.13524386388251097}, {"annotation_id": "7b6aff71-439e-4ec6-b615-8afb25797823", "tile_id": "tile_15_14", "x": 15, "y": 14, "xmin": 37368.0, "ymin": 55329.3, "xmax": 37641.2, "ymax": 55567.25, "lymphome_probability": 0.7521980326199762}, {"annotation_id": "7b6aff71-439e-4ec6-b615-8afb25797823", "tile_id": "tile_15_15", "x": 15, "y": 15, "xmin": 37368.0, "ymin": 55567.25, "xmax": 37641.2, "ymax": 55805.2, "lymphome_probability": 0.20822583381598503}, {"annotation_id": "7b6aff71-439e-4ec6-b615-8afb25797823", "tile_id": "tile_15_16", "x": 15, "y": 16, "xmin": 37368.0, "ymin": 55805.2, "xmax": 37641.2, "ymax": 56043.15, "lymphome_probability": 0.8658504631032995}, {"annotation_id": "7b6aff71-439e-4ec6-b615-8afb25797823", "tile_id": "tile_15_17", "x": 15, "y": 17, "xmin": 37368.0, "ymin": 56043.15, "xmax": 37641.2, "ymax": 56281.1, "lymphome_probability": 0.2652007938132369}, {"annotation_id": "7b6aff71-439e-4ec6-b615-8afb25797823", "tile_id": "tile_15_18", "x": 15, "y": 18, "xmin": 37368.0, "ymin": 56281.1, "xmax": 37641.2, "ymax": 56519.05, "lymphome_probability": 0.6965217927437366}, {"annotation_id": "7b6aff71-439e-4ec6-b615-8afb25797823", "tile_id": "tile_15_19", "x": 15, "y": 19, "xmin": 37368.0, "ymin": 56519.05, "xmax": 37641.2, "ymax": 56757.0, "lymphome_probability": 0.4082622674556221}, {"annotation_id": "7b6aff71-439e-4ec6-b615-8afb25797823", "tile_id": "tile_16_0", "x": 16, "y": 0, "xmin": 37641.2, "ymin": 51998.0, "xmax": 37914.4, "ymax": 52235.95, "lymphome_probability": 0.7327481309842705}, {"annotation_id": "7b6aff71-439e-4ec6-b615-8afb25797823", "tile_id": "tile_16_1", "x": 16, "y": 1, "xmin": 37641.2, "ymin": 52235.95, "xmax": 37914.4, "ymax": 52473.9, "lymphome_probability": 0.4894979159014392}, {"annotation_id": "7b6aff71-439e-4ec6-b615-8afb25797823", "tile_id": "tile_16_2", "x": 16, "y": 2, "xmin": 37641.2, "ymin": 52473.9, "xmax": 37914.4, "ymax": 52711.85, "lymphome_probability": 0.562036734558263}, {"annotation_id": "7b6aff71-439e-4ec6-b615-8afb25797823", "tile_id": "tile_16_3", "x": 16, "y": 3, "xmin": 37641.2, "ymin": 52711.85, "xmax": 37914.4, "ymax": 52949.8, "lymphome_probability": 0.5605550869803623}, {"annotation_id": "7b6aff71-439e-4ec6-b615-8afb25797823", "tile_id": "tile_16_4", "x": 16, "y": 4, "xmin": 37641.2, "ymin": 52949.8, "xmax": 37914.4, "ymax": 53187.75, "lymphome_probability": 0.35163519553926936}, {"annotation_id": "7b6aff71-439e-4ec6-b615-8afb25797823", "tile_id": "tile_16_5", "x": 16, "y": 5, "xmin": 37641.2, "ymin": 53187.75, "xmax": 37914.4, "ymax": 53425.7, "lymphome_probability": 0.8393706206514145}, {"annotation_id": "7b6aff71-439e-4ec6-b615-8afb25797823", "tile_id": "tile_16_6", "x": 16, "y": 6, "xmin": 37641.2, "ymin": 53425.7, "xmax": 37914.4, "ymax": 53663.65, "lymphome_probability": 0.5957685089767915}, {"annotation_id": "7b6aff71-439e-4ec6-b615-8afb25797823", "tile_id": "tile_16_7", "x": 16, "y": 7, "xmin": 37641.2, "ymin": 53663.65, "xmax": 37914.4, "ymax": 53901.6, "lymphome_probability": 0.06788368650856413}, {"annotation_id": "7b6aff71-439e-4ec6-b615-8afb25797823", "tile_id": "tile_16_8", "x": 16, "y": 8, "xmin": 37641.2, "ymin": 53901.6, "xmax": 37914.4, "ymax": 54139.55, "lymphome_probability": 0.5870599165406598}, {"annotation_id": "7b6aff71-439e-4ec6-b615-8afb25797823", "tile_id": "tile_16_9", "x": 16, "y": 9, "xmin": 37641.2, "ymin": 54139.55, "xmax": 37914.4, "ymax": 54377.5, "lymphome_probability": 0.5732281276306359}, {"annotation_id": "7b6aff71-439e-4ec6-b615-8afb25797823", "tile_id": "tile_16_10", "x": 16, "y": 10, "xmin": 37641.2, "ymin": 54377.5, "xmax": 37914.4, "ymax": 54615.45, "lymphome_probability": 0.42649074572710743}, {"annotation_id": "7b6aff71-439e-4ec6-b615-8afb25797823", "tile_id": "tile_16_11", "x": 16, "y": 11, "xmin": 37641.2, "ymin": 54615.45, "xmax": 37914.4, "ymax": 54853.4, "lymphome_probability": 0.6493733802151084}, {"annotation_id": "7b6aff71-439e-4ec6-b615-8afb25797823", "tile_id": "tile_16_12", "x": 16, "y": 12, "xmin": 37641.2, "ymin": 54853.4, "xmax": 37914.4, "ymax": 55091.35, "lymphome_probability": 0.6701376194068118}, {"annotation_id": "7b6aff71-439e-4ec6-b615-8afb25797823", "tile_id": "tile_16_13", "x": 16, "y": 13, "xmin": 37641.2, "ymin": 55091.35, "xmax": 37914.4, "ymax": 55329.3, "lymphome_probability": 0.8764037911269333}, {"annotation_id": "7b6aff71-439e-4ec6-b615-8afb25797823", "tile_id": "tile_16_14", "x": 16, "y": 14, "xmin": 37641.2, "ymin": 55329.3, "xmax": 37914.4, "ymax": 55567.25, "lymphome_probability": 0.40640192026203814}, {"annotation_id": "7b6aff71-439e-4ec6-b615-8afb25797823", "tile_id": "tile_16_15", "x": 16, "y": 15, "xmin": 37641.2, "ymin": 55567.25, "xmax": 37914.4, "ymax": 55805.2, "lymphome_probability": 0.8434356489411851}, {"annotation_id": "7b6aff71-439e-4ec6-b615-8afb25797823", "tile_id": "tile_16_16", "x": 16, "y": 16, "xmin": 37641.2, "ymin": 55805.2, "xmax": 37914.4, "ymax": 56043.15, "lymphome_probability": 0.2938523422272137}, {"annotation_id": "7b6aff71-439e-4ec6-b615-8afb25797823", "tile_id": "tile_16_17", "x": 16, "y": 17, "xmin": 37641.2, "ymin": 56043.15, "xmax": 37914.4, "ymax": 56281.1, "lymphome_probability": 0.30972936948914886}, {"annotation_id": "7b6aff71-439e-4ec6-b615-8afb25797823", "tile_id": "tile_16_18", "x": 16, "y": 18, "xmin": 37641.2, "ymin": 56281.1, "xmax": 37914.4, "ymax": 56519.05, "lymphome_probability": 0.4561921333948218}, {"annotation_id": "7b6aff71-439e-4ec6-b615-8afb25797823", "tile_id": "tile_16_19", "x": 16, "y": 19, "xmin": 37641.2, "ymin": 56519.05, "xmax": 37914.4, "ymax": 56757.0, "lymphome_probability": 0.0635999523271018}, {"annotation_id": "7b6aff71-439e-4ec6-b615-8afb25797823", "tile_id": "tile_17_0", "x": 17, "y": 0, "xmin": 37914.4, "ymin": 51998.0, "xmax": 38187.6, "ymax": 52235.95, "lymphome_probability": 0.4652349242895939}, {"annotation_id": "7b6aff71-439e-4ec6-b615-8afb25797823", "tile_id": "tile_17_1", "x": 17, "y": 1, "xmin": 37914.4, "ymin": 52235.95, "xmax": 38187.6, "ymax": 52473.9, "lymphome_probability": 0.37216423268281695}, {"annotation_id": "7b6aff71-439e-4ec6-b615-8afb25797823", "tile_id": "tile_17_2", "x": 17, "y": 2, "xmin": 37914.4, "ymin": 52473.9, "xmax": 38187.6, "ymax": 52711.85, "lymphome_probability": 0.42632802552380566}, {"annotation_id": "7b6aff71-439e-4ec6-b615-8afb25797823", "tile_id": "tile_17_3", "x": 17, "y": 3, "xmin": 37914.4, "ymin": 52711.85, "xmax": 38187.6, "ymax": 52949.8, "lymphome_probability": 0.6555382608658098}, {"annotation_id": "7b6aff71-439e-4ec6-b615-8afb25797823", "tile_id": "tile_17_4", "x": 17, "y": 4, "xmin": 37914.4, "ymin": 52949.8, "xmax": 38187.6, "ymax": 53187.75, "lymphome_probability": 0.835899526829455}, {"annotation_id": "7b6aff71-439e-4ec6-b615-8afb25797823", "tile_id": "tile_17_5", "x": 17, "y": 5, "xmin": 37914.4, "ymin": 53187.75, "xmax": 38187.6, "ymax": 53425.7, "lymphome_probability": 0.6102289147277165}, {"annotation_id": "7b6aff71-439e-4ec6-b615-8afb25797823", "tile_id": "tile_17_6", "x": 17, "y": 6, "xmin": 37914.4, "ymin": 53425.7, "xmax": 38187.6, "ymax": 53663.65, "lymphome_probability": 0.3544288464122408}, {"annotation_id": "7b6aff71-439e-4ec6-b615-8afb25797823", "tile_id": "tile_17_7", "x": 17, "y": 7, "xmin": 37914.4, "ymin": 53663.65, "xmax": 38187.6, "ymax": 53901.6, "lymphome_probability": 0.4036258785528042}, {"annotation_id": "7b6aff71-439e-4ec6-b615-8afb25797823", "tile_id": "tile_17_8", "x": 17, "y": 8, "xmin": 37914.4, "ymin": 53901.6, "xmax": 38187.6, "ymax": 54139.55, "lymphome_probability": 0.33583392443105453}, {"annotation_id": "7b6aff71-439e-4ec6-b615-8afb25797823", "tile_id": "tile_17_9", "x": 17, "y": 9, "xmin": 37914.4, "ymin": 54139.55, "xmax": 38187.6, "ymax": 54377.5, "lymphome_probability": 0.8184521433693405}, {"annotation_id": "7b6aff71-439e-4ec6-b615-8afb25797823", "tile_id": "tile_17_10", "x": 17, "y": 10, "xmin": 37914.4, "ymin": 54377.5, "xmax": 38187.6, "ymax": 54615.45, "lymphome_probability": 0.6907483731461729}, {"annotation_id": "7b6aff71-439e-4ec6-b615-8afb25797823", "tile_id": "tile_17_11", "x": 17, "y": 11, "xmin": 37914.4, "ymin": 54615.45, "xmax": 38187.6, "ymax": 54853.4, "lymphome_probability": 0.4789823340233069}, {"annotation_id": "7b6aff71-439e-4ec6-b615-8afb25797823", "tile_id": "tile_17_12", "x": 17, "y": 12, "xmin": 37914.4, "ymin": 54853.4, "xmax": 38187.6, "ymax": 55091.35, "lymphome_probability": 0.8952439046951987}, {"annotation_id": "7b6aff71-439e-4ec6-b615-8afb25797823", "tile_id": "tile_17_13", "x": 17, "y": 13, "xmin": 37914.4, "ymin": 55091.35, "xmax": 38187.6, "ymax": 55329.3, "lymphome_probability": 0.016815599384373492}, {"annotation_id": "7b6aff71-439e-4ec6-b615-8afb25797823", "tile_id": "tile_17_14", "x": 17, "y": 14, "xmin": 37914.4, "ymin": 55329.3, "xmax": 38187.6, "ymax": 55567.25, "lymphome_probability": 0.9357243284714366}, {"annotation_id": "7b6aff71-439e-4ec6-b615-8afb25797823", "tile_id": "tile_17_15", "x": 17, "y": 15, "xmin": 37914.4, "ymin": 55567.25, "xmax": 38187.6, "ymax": 55805.2, "lymphome_probability": 0.07580029000744726}, {"annotation_id": "7b6aff71-439e-4ec6-b615-8afb25797823", "tile_id": "tile_17_16", "x": 17, "y": 16, "xmin": 37914.4, "ymin": 55805.2, "xmax": 38187.6, "ymax": 56043.15, "lymphome_probability": 0.9496384268664165}, {"annotation_id": "7b6aff71-439e-4ec6-b615-8afb25797823", "tile_id": "tile_17_17", "x": 17, "y": 17, "xmin": 37914.4, "ymin": 56043.15, "xmax": 38187.6, "ymax": 56281.1, "lymphome_probability": 0.16126305831232113}, {"annotation_id": "7b6aff71-439e-4ec6-b615-8afb25797823", "tile_id": "tile_17_18", "x": 17, "y": 18, "xmin": 37914.4, "ymin": 56281.1, "xmax": 38187.6, "ymax": 56519.05, "lymphome_probability": 0.13499716143654883}, {"annotation_id": "7b6aff71-439e-4ec6-b615-8afb25797823", "tile_id": "tile_17_19", "x": 17, "y": 19, "xmin": 37914.4, "ymin": 56519.05, "xmax": 38187.6, "ymax": 56757.0, "lymphome_probability": 0.7850094409432435}, {"annotation_id": "7b6aff71-439e-4ec6-b615-8afb25797823", "tile_id": "tile_18_0", "x": 18, "y": 0, "xmin": 38187.6, "ymin": 51998.0, "xmax": 38460.8, "ymax": 52235.95, "lymphome_probability": 0.7191420548993211}, {"annotation_id": "7b6aff71-439e-4ec6-b615-8afb25797823", "tile_id": "tile_18_1", "x": 18, "y": 1, "xmin": 38187.6, "ymin": 52235.95, "xmax": 38460.8, "ymax": 52473.9, "lymphome_probability": 0.6177293645638455}, {"annotation_id": "7b6aff71-439e-4ec6-b615-8afb25797823", "tile_id": "tile_18_2", "x": 18, "y": 2, "xmin": 38187.6, "ymin": 52473.9, "xmax": 38460.8, "ymax": 52711.85, "lymphome_probability": 0.6171857549071215}, {"annotation_id": "7b6aff71-439e-4ec6-b615-8afb25797823", "tile_id": "tile_18_3", "x": 18, "y": 3, "xmin": 38187.6, "ymin": 52711.85, "xmax": 38460.8, "ymax": 52949.8, "lymphome_probability": 0.5032757953767998}, {"annotation_id": "7b6aff71-439e-4ec6-b615-8afb25797823", "tile_id": "tile_18_4", "x": 18, "y": 4, "xmin": 38187.6, "ymin": 52949.8, "xmax": 38460.8, "ymax": 53187.75, "lymphome_probability": 0.9996111799866616}, {"annotation_id": "7b6aff71-439e-4ec6-b615-8afb25797823", "tile_id": "tile_18_5", "x": 18, "y": 5, "xmin": 38187.6, "ymin": 53187.75, "xmax": 38460.8, "ymax": 53425.7, "lymphome_probability": 0.14371083955045827}, {"annotation_id": "7b6aff71-439e-4ec6-b615-8afb25797823", "tile_id": "tile_18_6", "x": 18, "y": 6, "xmin": 38187.6, "ymin": 53425.7, "xmax": 38460.8, "ymax": 53663.65, "lymphome_probability": 0.20635624785851103}, {"annotation_id": "7b6aff71-439e-4ec6-b615-8afb25797823", "tile_id": "tile_18_7", "x": 18, "y": 7, "xmin": 38187.6, "ymin": 53663.65, "xmax": 38460.8, "ymax": 53901.6, "lymphome_probability": 0.6149368798950053}, {"annotation_id": "7b6aff71-439e-4ec6-b615-8afb25797823", "tile_id": "tile_18_8", "x": 18, "y": 8, "xmin": 38187.6, "ymin": 53901.6, "xmax": 38460.8, "ymax": 54139.55, "lymphome_probability": 0.3226594217398452}, {"annotation_id": "7b6aff71-439e-4ec6-b615-8afb25797823", "tile_id": "tile_18_9", "x": 18, "y": 9, "xmin": 38187.6, "ymin": 54139.55, "xmax": 38460.8, "ymax": 54377.5, "lymphome_probability": 0.14930228062495943}, {"annotation_id": "7b6aff71-439e-4ec6-b615-8afb25797823", "tile_id": "tile_18_10", "x": 18, "y": 10, "xmin": 38187.6, "ymin": 54377.5, "xmax": 38460.8, "ymax": 54615.45, "lymphome_probability": 0.9527059523156781}, {"annotation_id": "7b6aff71-439e-4ec6-b615-8afb25797823", "tile_id": "tile_18_11", "x": 18, "y": 11, "xmin": 38187.6, "ymin": 54615.45, "xmax": 38460.8, "ymax": 54853.4, "lymphome_probability": 0.3632590731333849}, {"annotation_id": "7b6aff71-439e-4ec6-b615-8afb25797823", "tile_id": "tile_18_12", "x": 18, "y": 12, "xmin": 38187.6, "ymin": 54853.4, "xmax": 38460.8, "ymax": 55091.35, "lymphome_probability": 0.844132144177188}, {"annotation_id": "7b6aff71-439e-4ec6-b615-8afb25797823", "tile_id": "tile_18_13", "x": 18, "y": 13, "xmin": 38187.6, "ymin": 55091.35, "xmax": 38460.8, "ymax": 55329.3, "lymphome_probability": 0.538385631947713}, {"annotation_id": "7b6aff71-439e-4ec6-b615-8afb25797823", "tile_id": "tile_18_14", "x": 18, "y": 14, "xmin": 38187.6, "ymin": 55329.3, "xmax": 38460.8, "ymax": 55567.25, "lymphome_probability": 0.6236434463695254}, {"annotation_id": "7b6aff71-439e-4ec6-b615-8afb25797823", "tile_id": "tile_18_15", "x": 18, "y": 15, "xmin": 38187.6, "ymin": 55567.25, "xmax": 38460.8, "ymax": 55805.2, "lymphome_probability": 0.4949349930642062}, {"annotation_id": "7b6aff71-439e-4ec6-b615-8afb25797823", "tile_id": "tile_18_16", "x": 18, "y": 16, "xmin": 38187.6, "ymin": 55805.2, "xmax": 38460.8, "ymax": 56043.15, "lymphome_probability": 0.152947594591478}, {"annotation_id": "7b6aff71-439e-4ec6-b615-8afb25797823", "tile_id": "tile_18_17", "x": 18, "y": 17, "xmin": 38187.6, "ymin": 56043.15, "xmax": 38460.8, "ymax": 56281.1, "lymphome_probability": 0.32708198666290766}, {"annotation_id": "7b6aff71-439e-4ec6-b615-8afb25797823", "tile_id": "tile_18_18", "x": 18, "y": 18, "xmin": 38187.6, "ymin": 56281.1, "xmax": 38460.8, "ymax": 56519.05, "lymphome_probability": 0.550735852302839}, {"annotation_id": "7b6aff71-439e-4ec6-b615-8afb25797823", "tile_id": "tile_18_19", "x": 18, "y": 19, "xmin": 38187.6, "ymin": 56519.05, "xmax": 38460.8, "ymax": 56757.0, "lymphome_probability": 0.4519207774303238}, {"annotation_id": "7b6aff71-439e-4ec6-b615-8afb25797823", "tile_id": "tile_19_0", "x": 19, "y": 0, "xmin": 38460.8, "ymin": 51998.0, "xmax": 38734.0, "ymax": 52235.95, "lymphome_probability": 0.6161092352242699}, {"annotation_id": "7b6aff71-439e-4ec6-b615-8afb25797823", "tile_id": "tile_19_1", "x": 19, "y": 1, "xmin": 38460.8, "ymin": 52235.95, "xmax": 38734.0, "ymax": 52473.9, "lymphome_probability": 0.10920896769892874}, {"annotation_id": "7b6aff71-439e-4ec6-b615-8afb25797823", "tile_id": "tile_19_2", "x": 19, "y": 2, "xmin": 38460.8, "ymin": 52473.9, "xmax": 38734.0, "ymax": 52711.85, "lymphome_probability": 0.48077308254132123}, {"annotation_id": "7b6aff71-439e-4ec6-b615-8afb25797823", "tile_id": "tile_19_3", "x": 19, "y": 3, "xmin": 38460.8, "ymin": 52711.85, "xmax": 38734.0, "ymax": 52949.8, "lymphome_probability": 0.10782953430655406}, {"annotation_id": "7b6aff71-439e-4ec6-b615-8afb25797823", "tile_id": "tile_19_4", "x": 19, "y": 4, "xmin": 38460.8, "ymin": 52949.8, "xmax": 38734.0, "ymax": 53187.75, "lymphome_probability": 0.3288270871596336}, {"annotation_id": "7b6aff71-439e-4ec6-b615-8afb25797823", "tile_id": "tile_19_5", "x": 19, "y": 5, "xmin": 38460.8, "ymin": 53187.75, "xmax": 38734.0, "ymax": 53425.7, "lymphome_probability": 0.09562928613954491}, {"annotation_id": "7b6aff71-439e-4ec6-b615-8afb25797823", "tile_id": "tile_19_6", "x": 19, "y": 6, "xmin": 38460.8, "ymin": 53425.7, "xmax": 38734.0, "ymax": 53663.65, "lymphome_probability": 0.6583877176806077}, {"annotation_id": "7b6aff71-439e-4ec6-b615-8afb25797823", "tile_id": "tile_19_7", "x": 19, "y": 7, "xmin": 38460.8, "ymin": 53663.65, "xmax": 38734.0, "ymax": 53901.6, "lymphome_probability": 0.3394732913268863}, {"annotation_id": "7b6aff71-439e-4ec6-b615-8afb25797823", "tile_id": "tile_19_8", "x": 19, "y": 8, "xmin": 38460.8, "ymin": 53901.6, "xmax": 38734.0, "ymax": 54139.55, "lymphome_probability": 0.6419380266540614}, {"annotation_id": "7b6aff71-439e-4ec6-b615-8afb25797823", "tile_id": "tile_19_9", "x": 19, "y": 9, "xmin": 38460.8, "ymin": 54139.55, "xmax": 38734.0, "ymax": 54377.5, "lymphome_probability": 0.8663310300325703}, {"annotation_id": "7b6aff71-439e-4ec6-b615-8afb25797823", "tile_id": "tile_19_10", "x": 19, "y": 10, "xmin": 38460.8, "ymin": 54377.5, "xmax": 38734.0, "ymax": 54615.45, "lymphome_probability": 0.5461625732419755}, {"annotation_id": "7b6aff71-439e-4ec6-b615-8afb25797823", "tile_id": "tile_19_11", "x": 19, "y": 11, "xmin": 38460.8, "ymin": 54615.45, "xmax": 38734.0, "ymax": 54853.4, "lymphome_probability": 0.3511110183669969}, {"annotation_id": "7b6aff71-439e-4ec6-b615-8afb25797823", "tile_id": "tile_19_12", "x": 19, "y": 12, "xmin": 38460.8, "ymin": 54853.4, "xmax": 38734.0, "ymax": 55091.35, "lymphome_probability": 0.9724109369265113}, {"annotation_id": "7b6aff71-439e-4ec6-b615-8afb25797823", "tile_id": "tile_19_13", "x": 19, "y": 13, "xmin": 38460.8, "ymin": 55091.35, "xmax": 38734.0, "ymax": 55329.3, "lymphome_probability": 0.9875242646473253}, {"annotation_id": "7b6aff71-439e-4ec6-b615-8afb25797823", "tile_id": "tile_19_14", "x": 19, "y": 14, "xmin": 38460.8, "ymin": 55329.3, "xmax": 38734.0, "ymax": 55567.25, "lymphome_probability": 0.2250727666255774}, {"annotation_id": "7b6aff71-439e-4ec6-b615-8afb25797823", "tile_id": "tile_19_15", "x": 19, "y": 15, "xmin": 38460.8, "ymin": 55567.25, "xmax": 38734.0, "ymax": 55805.2, "lymphome_probability": 0.7014507988865224}, {"annotation_id": "7b6aff71-439e-4ec6-b615-8afb25797823", "tile_id": "tile_19_16", "x": 19, "y": 16, "xmin": 38460.8, "ymin": 55805.2, "xmax": 38734.0, "ymax": 56043.15, "lymphome_probability": 0.884198657722239}, {"annotation_id": "7b6aff71-439e-4ec6-b615-8afb25797823", "tile_id": "tile_19_17", "x": 19, "y": 17, "xmin": 38460.8, "ymin": 56043.15, "xmax": 38734.0, "ymax": 56281.1, "lymphome_probability": 0.6560668394923205}, {"annotation_id": "7b6aff71-439e-4ec6-b615-8afb25797823", "tile_id": "tile_19_18", "x": 19, "y": 18, "xmin": 38460.8, "ymin": 56281.1, "xmax": 38734.0, "ymax": 56519.05, "lymphome_probability": 0.6265665421689064}, {"annotation_id": "7b6aff71-439e-4ec6-b615-8afb25797823", "tile_id": "tile_19_19", "x": 19, "y": 19, "xmin": 38460.8, "ymin": 56519.05, "xmax": 38734.0, "ymax": 56757.0, "lymphome_probability": 0.6314536710298904}]}